{
"meta":{"test_sets":[],"test_metrics":[],"learn_metrics":[{"best_value":"Min","name":"RMSE"}],"launch_mode":"Train","parameters":"","iteration_count":1000,"learn_sets":["learn"],"name":"experiment"},
"iterations":[
{"learn":[14.61268541],"iteration":0,"passed_time":0.1419166242,"remaining_time":141.7747076},
{"learn":[14.23196558],"iteration":1,"passed_time":0.1427757928,"remaining_time":71.24512059},
{"learn":[13.86674177],"iteration":2,"passed_time":0.1435248771,"remaining_time":47.69810081},
{"learn":[13.49946468],"iteration":3,"passed_time":0.1441258717,"remaining_time":35.88734206},
{"learn":[13.16661202],"iteration":4,"passed_time":0.1447433264,"remaining_time":28.80392195},
{"learn":[12.85632158],"iteration":5,"passed_time":0.1453292353,"remaining_time":24.07620998},
{"learn":[12.56784336],"iteration":6,"passed_time":0.1459535808,"remaining_time":20.70455797},
{"learn":[12.31617801],"iteration":7,"passed_time":0.1466715005,"remaining_time":18.18726606},
{"learn":[12.01509946],"iteration":8,"passed_time":0.1472803691,"remaining_time":16.21720509},
{"learn":[11.71512571],"iteration":9,"passed_time":0.1478675418,"remaining_time":14.63888664},
{"learn":[11.43264457],"iteration":10,"passed_time":0.1484867418,"remaining_time":13.35030796},
{"learn":[11.17973129],"iteration":11,"passed_time":0.1490486578,"remaining_time":12.27167283},
{"learn":[10.93746433],"iteration":12,"passed_time":0.1496446573,"remaining_time":11.36148283},
{"learn":[10.69387075],"iteration":13,"passed_time":0.1502866264,"remaining_time":10.5844724},
{"learn":[10.4615922],"iteration":14,"passed_time":0.150941605,"remaining_time":9.91183206},
{"learn":[10.2299235],"iteration":15,"passed_time":0.151683678,"remaining_time":9.328546196},
{"learn":[10.01419731],"iteration":16,"passed_time":0.1526418182,"remaining_time":8.826288667},
{"learn":[9.795856918],"iteration":17,"passed_time":0.1534955503,"remaining_time":8.37403502},
{"learn":[9.60040151],"iteration":18,"passed_time":0.1543122686,"remaining_time":7.967386081},
{"learn":[9.418664989],"iteration":19,"passed_time":0.1550476325,"remaining_time":7.597333994},
{"learn":[9.249278645],"iteration":20,"passed_time":0.1557959545,"remaining_time":7.263059022},
{"learn":[9.090113396],"iteration":21,"passed_time":0.156481205,"remaining_time":6.956300841},
{"learn":[8.909548708],"iteration":22,"passed_time":0.157090525,"remaining_time":6.672932299},
{"learn":[8.740140208],"iteration":23,"passed_time":0.1577778565,"remaining_time":6.416299496},
{"learn":[8.59377682],"iteration":24,"passed_time":0.1586408616,"remaining_time":6.186993603},
{"learn":[8.453885414],"iteration":25,"passed_time":0.1593228622,"remaining_time":5.968479532},
{"learn":[8.317732234],"iteration":26,"passed_time":0.1599709499,"remaining_time":5.764879047},
{"learn":[8.180896085],"iteration":27,"passed_time":0.1605959976,"remaining_time":5.574975346},
{"learn":[8.053220863],"iteration":28,"passed_time":0.1611775834,"remaining_time":5.396670119},
{"learn":[7.924234474],"iteration":29,"passed_time":0.1617088463,"remaining_time":5.228586031},
{"learn":[7.818879511],"iteration":30,"passed_time":0.1623154179,"remaining_time":5.073665806},
{"learn":[7.719346395],"iteration":31,"passed_time":0.1629699151,"remaining_time":4.929839931},
{"learn":[7.624163594],"iteration":32,"passed_time":0.1638026853,"remaining_time":4.799915051},
{"learn":[7.524952543],"iteration":33,"passed_time":0.1644937535,"remaining_time":4.673557819},
{"learn":[7.424464745],"iteration":34,"passed_time":0.1651251003,"remaining_time":4.552734908},
{"learn":[7.327482321],"iteration":35,"passed_time":0.1657764779,"remaining_time":4.439125687},
{"learn":[7.238666841],"iteration":36,"passed_time":0.1663573114,"remaining_time":4.32978624},
{"learn":[7.158842395],"iteration":37,"passed_time":0.1669745354,"remaining_time":4.227092185},
{"learn":[7.074348246],"iteration":38,"passed_time":0.1675697525,"remaining_time":4.129090568},
{"learn":[6.992269093],"iteration":39,"passed_time":0.1682112288,"remaining_time":4.037069492},
{"learn":[6.925219745],"iteration":40,"passed_time":0.1688512721,"remaining_time":3.949472437},
{"learn":[6.86013671],"iteration":41,"passed_time":0.1695319126,"remaining_time":3.866942198},
{"learn":[6.786739622],"iteration":42,"passed_time":0.1702036722,"remaining_time":3.788021262},
{"learn":[6.73057926],"iteration":43,"passed_time":0.1708749603,"remaining_time":3.712646864},
{"learn":[6.666356486],"iteration":44,"passed_time":0.1716596063,"remaining_time":3.642998311},
{"learn":[6.606182832],"iteration":45,"passed_time":0.1723344953,"remaining_time":3.574067576},
{"learn":[6.547854615],"iteration":46,"passed_time":0.1730827304,"remaining_time":3.509528556},
{"learn":[6.49240675],"iteration":47,"passed_time":0.1738613005,"remaining_time":3.448249127},
{"learn":[6.431317261],"iteration":48,"passed_time":0.1746093015,"remaining_time":3.388845832},
{"learn":[6.377586395],"iteration":49,"passed_time":0.1753732209,"remaining_time":3.332091196},
{"learn":[6.327558015],"iteration":50,"passed_time":0.1762051467,"remaining_time":3.278797729},
{"learn":[6.282040317],"iteration":51,"passed_time":0.1771006151,"remaining_time":3.228680444},
{"learn":[6.237655841],"iteration":52,"passed_time":0.177874705,"remaining_time":3.178251804},
{"learn":[6.192792003],"iteration":53,"passed_time":0.1788646819,"remaining_time":3.133444242},
{"learn":[6.150579347],"iteration":54,"passed_time":0.1796839897,"remaining_time":3.087297641},
{"learn":[6.115693845],"iteration":55,"passed_time":0.1804577975,"remaining_time":3.042002872},
{"learn":[6.078780782],"iteration":56,"passed_time":0.1811448334,"remaining_time":2.9968347},
{"learn":[6.045146957],"iteration":57,"passed_time":0.1820028046,"remaining_time":2.955976584},
{"learn":[6.008080327],"iteration":58,"passed_time":0.1829158708,"remaining_time":2.917353125},
{"learn":[5.977575734],"iteration":59,"passed_time":0.183829962,"remaining_time":2.880002738},
{"learn":[5.948036502],"iteration":60,"passed_time":0.1845962485,"remaining_time":2.84157176},
{"learn":[5.914888282],"iteration":61,"passed_time":0.1853265759,"remaining_time":2.803811744},
{"learn":[5.884957796],"iteration":62,"passed_time":0.1860670293,"remaining_time":2.76737788},
{"learn":[5.849539885],"iteration":63,"passed_time":0.1867383274,"remaining_time":2.731048038},
{"learn":[5.821387627],"iteration":64,"passed_time":0.1873543577,"remaining_time":2.695020376},
{"learn":[5.797012279],"iteration":65,"passed_time":0.1883343619,"remaining_time":2.665216575},
{"learn":[5.768685095],"iteration":66,"passed_time":0.1892104978,"remaining_time":2.634826783},
{"learn":[5.755484587],"iteration":67,"passed_time":0.1896290787,"remaining_time":2.599033843},
{"learn":[5.731887055],"iteration":68,"passed_time":0.1903539294,"remaining_time":2.568398671},
{"learn":[5.707148487],"iteration":69,"passed_time":0.1911877108,"remaining_time":2.540065301},
{"learn":[5.685365039],"iteration":70,"passed_time":0.1919001279,"remaining_time":2.510918575},
{"learn":[5.663541834],"iteration":71,"passed_time":0.1926368305,"remaining_time":2.482874704},
{"learn":[5.638108797],"iteration":72,"passed_time":0.193354028,"remaining_time":2.455331287},
{"learn":[5.619204893],"iteration":73,"passed_time":0.1942552094,"remaining_time":2.430815188},
{"learn":[5.598472793],"iteration":74,"passed_time":0.1950872267,"remaining_time":2.406075796},
{"learn":[5.577007075],"iteration":75,"passed_time":0.1959534915,"remaining_time":2.382381923},
{"learn":[5.562637084],"iteration":76,"passed_time":0.1967157859,"remaining_time":2.35803468},
{"learn":[5.54729991],"iteration":77,"passed_time":0.1975092048,"remaining_time":2.334660087},
{"learn":[5.530737623],"iteration":78,"passed_time":0.1982488604,"remaining_time":2.311230386},
{"learn":[5.513704873],"iteration":79,"passed_time":0.1989561077,"remaining_time":2.287995239},
{"learn":[5.501575529],"iteration":80,"passed_time":0.1996654815,"remaining_time":2.265340462},
{"learn":[5.484080734],"iteration":81,"passed_time":0.2004514578,"remaining_time":2.244078515},
{"learn":[5.472178894],"iteration":82,"passed_time":0.2012613567,"remaining_time":2.223574266},
{"learn":[5.458923342],"iteration":83,"passed_time":0.2020197292,"remaining_time":2.202977047},
{"learn":[5.451382371],"iteration":84,"passed_time":0.202559177,"remaining_time":2.180489964},
{"learn":[5.441410748],"iteration":85,"passed_time":0.2031614255,"remaining_time":2.159180731},
{"learn":[5.434047468],"iteration":86,"passed_time":0.2035990441,"remaining_time":2.136619854},
{"learn":[5.422107497],"iteration":87,"passed_time":0.2042054653,"remaining_time":2.116311186},
{"learn":[5.40731265],"iteration":88,"passed_time":0.2051531124,"remaining_time":2.099938039},
{"learn":[5.396360181],"iteration":89,"passed_time":0.2057996755,"remaining_time":2.080863385},
{"learn":[5.383793239],"iteration":90,"passed_time":0.2066379556,"remaining_time":2.064108809},
{"learn":[5.369605034],"iteration":91,"passed_time":0.2075416292,"remaining_time":2.048345645},
{"learn":[5.357467333],"iteration":92,"passed_time":0.2083204538,"remaining_time":2.031684426},
{"learn":[5.341109968],"iteration":93,"passed_time":0.2090530982,"remaining_time":2.014916031},
{"learn":[5.330529276],"iteration":94,"passed_time":0.2098163342,"remaining_time":1.998776657},
{"learn":[5.319862075],"iteration":95,"passed_time":0.2104518537,"remaining_time":1.981754956},
{"learn":[5.313052243],"iteration":96,"passed_time":0.2111336337,"remaining_time":1.965501765},
{"learn":[5.299677207],"iteration":97,"passed_time":0.2116893609,"remaining_time":1.948406158},
{"learn":[5.287546698],"iteration":98,"passed_time":0.2122736348,"remaining_time":1.931904495},
{"learn":[5.279803754],"iteration":99,"passed_time":0.2131140273,"remaining_time":1.918026245},
{"learn":[5.272254612],"iteration":100,"passed_time":0.2139354013,"remaining_time":1.904236889},
{"learn":[5.268813888],"iteration":101,"passed_time":0.2143359976,"remaining_time":1.886997312},
{"learn":[5.258113767],"iteration":102,"passed_time":0.2150760344,"remaining_time":1.873040805},
{"learn":[5.251018576],"iteration":103,"passed_time":0.21580947,"remaining_time":1.859281587},
{"learn":[5.24171237],"iteration":104,"passed_time":0.2164765954,"remaining_time":1.845205266},
{"learn":[5.233984943],"iteration":105,"passed_time":0.2170130943,"remaining_time":1.830280248},
{"learn":[5.226240449],"iteration":106,"passed_time":0.2175756924,"remaining_time":1.815841993},
{"learn":[5.220541644],"iteration":107,"passed_time":0.2181975303,"remaining_time":1.802149973},
{"learn":[5.211712096],"iteration":108,"passed_time":0.2190438408,"remaining_time":1.79053268},
{"learn":[5.203388597],"iteration":109,"passed_time":0.2199381093,"remaining_time":1.779499248},
{"learn":[5.196026544],"iteration":110,"passed_time":0.2206923847,"remaining_time":1.767527297},
{"learn":[5.188716772],"iteration":111,"passed_time":0.2214597755,"remaining_time":1.755859648},
{"learn":[5.182163132],"iteration":112,"passed_time":0.2221961114,"remaining_time":1.744141157},
{"learn":[5.17764747],"iteration":113,"passed_time":0.2228736472,"remaining_time":1.732158346},
{"learn":[5.170548056],"iteration":114,"passed_time":0.223494684,"remaining_time":1.719937351},
{"learn":[5.165901827],"iteration":115,"passed_time":0.224045921,"remaining_time":1.707384433},
{"learn":[5.160333668],"iteration":116,"passed_time":0.2247614534,"remaining_time":1.69627661},
{"learn":[5.148953243],"iteration":117,"passed_time":0.2257997041,"remaining_time":1.68775711},
{"learn":[5.144729126],"iteration":118,"passed_time":0.2264580934,"remaining_time":1.676551095},
{"learn":[5.139939946],"iteration":119,"passed_time":0.2272383185,"remaining_time":1.666414335},
{"learn":[5.132898872],"iteration":120,"passed_time":0.2278454116,"remaining_time":1.655174519},
{"learn":[5.129073077],"iteration":121,"passed_time":0.2284609405,"remaining_time":1.644169719},
{"learn":[5.127123916],"iteration":122,"passed_time":0.2289459069,"remaining_time":1.63240293},
{"learn":[5.121282057],"iteration":123,"passed_time":0.2296553869,"remaining_time":1.622404185},
{"learn":[5.114489821],"iteration":124,"passed_time":0.2302839653,"remaining_time":1.611987757},
{"learn":[5.107777291],"iteration":125,"passed_time":0.2308026802,"remaining_time":1.600964623},
{"learn":[5.103518754],"iteration":126,"passed_time":0.2317076838,"remaining_time":1.592762268},
{"learn":[5.101133351],"iteration":127,"passed_time":0.2322939638,"remaining_time":1.582502629},
{"learn":[5.096462705],"iteration":128,"passed_time":0.2331066967,"remaining_time":1.57392196},
{"learn":[5.08562082],"iteration":129,"passed_time":0.2341001015,"remaining_time":1.56666991},
{"learn":[5.080483682],"iteration":130,"passed_time":0.2349874656,"remaining_time":1.558809982},
{"learn":[5.07437499],"iteration":131,"passed_time":0.2358032625,"remaining_time":1.55058509},
{"learn":[5.070683732],"iteration":132,"passed_time":0.2366806748,"remaining_time":1.542873271},
{"learn":[5.06432037],"iteration":133,"passed_time":0.2378510987,"remaining_time":1.5371571},
{"learn":[5.057436484],"iteration":134,"passed_time":0.2387615429,"remaining_time":1.529842478},
{"learn":[5.053254656],"iteration":135,"passed_time":0.2395567472,"remaining_time":1.521889923},
{"learn":[5.04801663],"iteration":136,"passed_time":0.2403355316,"remaining_time":1.513938422},
{"learn":[5.045680836],"iteration":137,"passed_time":0.240912373,"remaining_time":1.50482946},
{"learn":[5.041857933],"iteration":138,"passed_time":0.2416346117,"remaining_time":1.49674389},
{"learn":[5.035264888],"iteration":139,"passed_time":0.2423350383,"remaining_time":1.488629521},
{"learn":[5.028771948],"iteration":140,"passed_time":0.2430634197,"remaining_time":1.480790621},
{"learn":[5.024912247],"iteration":141,"passed_time":0.2439413104,"remaining_time":1.473955242},
{"learn":[5.02239068],"iteration":142,"passed_time":0.244846714,"remaining_time":1.467368069},
{"learn":[5.017110572],"iteration":143,"passed_time":0.245684322,"remaining_time":1.460456803},
{"learn":[5.010707886],"iteration":144,"passed_time":0.2464932784,"remaining_time":1.453460366},
{"learn":[5.004389868],"iteration":145,"passed_time":0.2472051297,"remaining_time":1.44598069},
{"learn":[4.997628683],"iteration":146,"passed_time":0.2480627269,"remaining_time":1.439438816},
{"learn":[4.991497851],"iteration":147,"passed_time":0.2488158998,"remaining_time":1.432372612},
{"learn":[4.988345253],"iteration":148,"passed_time":0.2496273325,"remaining_time":1.425723892},
{"learn":[4.98460423],"iteration":149,"passed_time":0.2505453807,"remaining_time":1.419757157},
{"learn":[4.982441783],"iteration":150,"passed_time":0.251419635,"remaining_time":1.41361106},
{"learn":[4.977461771],"iteration":151,"passed_time":0.2522002663,"remaining_time":1.407012012},
{"learn":[4.973601586],"iteration":152,"passed_time":0.2529161787,"remaining_time":1.400130741},
{"learn":[4.968328804],"iteration":153,"passed_time":0.253574708,"remaining_time":1.393014305},
{"learn":[4.9640736],"iteration":154,"passed_time":0.2542012102,"remaining_time":1.385806597},
{"learn":[4.960865882],"iteration":155,"passed_time":0.2548468404,"remaining_time":1.378786752},
{"learn":[4.957014156],"iteration":156,"passed_time":0.2554766224,"remaining_time":1.371763011},
{"learn":[4.952244852],"iteration":157,"passed_time":0.2563071841,"remaining_time":1.365890184},
{"learn":[4.949695675],"iteration":158,"passed_time":0.2570710031,"remaining_time":1.359727759},
{"learn":[4.946584698],"iteration":159,"passed_time":0.257966602,"remaining_time":1.35432466},
{"learn":[4.940192834],"iteration":160,"passed_time":0.2587159207,"remaining_time":1.348215264},
{"learn":[4.936727994],"iteration":161,"passed_time":0.2594783258,"remaining_time":1.342239734},
{"learn":[4.932342063],"iteration":162,"passed_time":0.260238525,"remaining_time":1.336316843},
{"learn":[4.925830838],"iteration":163,"passed_time":0.2609507061,"remaining_time":1.330212136},
{"learn":[4.922571773],"iteration":164,"passed_time":0.2617824325,"remaining_time":1.324777764},
{"learn":[4.918395814],"iteration":165,"passed_time":0.2627821023,"remaining_time":1.32024261},
{"learn":[4.911142452],"iteration":166,"passed_time":0.2635763073,"remaining_time":1.314724934},
{"learn":[4.908276131],"iteration":167,"passed_time":0.2643258392,"remaining_time":1.309042251},
{"learn":[4.904584645],"iteration":168,"passed_time":0.2650845267,"remaining_time":1.303462969},
{"learn":[4.89795517],"iteration":169,"passed_time":0.2657795365,"remaining_time":1.297629502},
{"learn":[4.895556491],"iteration":170,"passed_time":0.2664806668,"remaining_time":1.291885806},
{"learn":[4.890591233],"iteration":171,"passed_time":0.2670812603,"remaining_time":1.285716765},
{"learn":[4.884629277],"iteration":172,"passed_time":0.267672706,"remaining_time":1.279568369},
{"learn":[4.880550786],"iteration":173,"passed_time":0.2687171417,"remaining_time":1.275634247},
{"learn":[4.876384842],"iteration":174,"passed_time":0.2695374162,"remaining_time":1.27067639},
{"learn":[4.872638238],"iteration":175,"passed_time":0.2703550084,"remaining_time":1.265752994},
{"learn":[4.869137118],"iteration":176,"passed_time":0.2710290148,"remaining_time":1.260208357},
{"learn":[4.863587157],"iteration":177,"passed_time":0.2717169936,"remaining_time":1.25478297},
{"learn":[4.858028614],"iteration":178,"passed_time":0.2722608648,"remaining_time":1.248749553},
{"learn":[4.853838176],"iteration":179,"passed_time":0.2728125197,"remaining_time":1.24281259},
{"learn":[4.853462329],"iteration":180,"passed_time":0.2731249683,"remaining_time":1.235852757},
{"learn":[4.851573196],"iteration":181,"passed_time":0.2737321719,"remaining_time":1.23029075},
{"learn":[4.848442087],"iteration":182,"passed_time":0.2746075302,"remaining_time":1.225980066},
{"learn":[4.845547104],"iteration":183,"passed_time":0.2755317753,"remaining_time":1.221923525},
{"learn":[4.839868817],"iteration":184,"passed_time":0.2763172811,"remaining_time":1.217289644},
{"learn":[4.836336958],"iteration":185,"passed_time":0.2774471553,"remaining_time":1.214204217},
{"learn":[4.831124789],"iteration":186,"passed_time":0.2781821734,"remaining_time":1.209423032},
{"learn":[4.827407333],"iteration":187,"passed_time":0.278778193,"remaining_time":1.204084536},
{"learn":[4.824088918],"iteration":188,"passed_time":0.2793663186,"remaining_time":1.198762351},
{"learn":[4.820934539],"iteration":189,"passed_time":0.2799894605,"remaining_time":1.193639279},
{"learn":[4.816975227],"iteration":190,"passed_time":0.280890615,"remaining_time":1.189740877},
{"learn":[4.812340486],"iteration":191,"passed_time":0.2816522969,"remaining_time":1.185286749},
{"learn":[4.806402747],"iteration":192,"passed_time":0.2823141965,"remaining_time":1.180453661},
{"learn":[4.801521788],"iteration":193,"passed_time":0.2829473287,"remaining_time":1.175544057},
{"learn":[4.797601172],"iteration":194,"passed_time":0.2835215321,"remaining_time":1.170435043},
{"learn":[4.792694629],"iteration":195,"passed_time":0.2841219751,"remaining_time":1.165479939},
{"learn":[4.789794613],"iteration":196,"passed_time":0.2846908422,"remaining_time":1.160440337},
{"learn":[4.785367055],"iteration":197,"passed_time":0.2853071443,"remaining_time":1.155638029},
{"learn":[4.780376856],"iteration":198,"passed_time":0.28610611,"remaining_time":1.151613036},
{"learn":[4.776691261],"iteration":199,"passed_time":0.2869076038,"remaining_time":1.147630415},
{"learn":[4.773470753],"iteration":200,"passed_time":0.2878035327,"remaining_time":1.144054839},
{"learn":[4.77207327],"iteration":201,"passed_time":0.2885879241,"remaining_time":1.140065166},
{"learn":[4.767347177],"iteration":202,"passed_time":0.2894247661,"remaining_time":1.136312998},
{"learn":[4.763983068],"iteration":203,"passed_time":0.2902635362,"remaining_time":1.132596935},
{"learn":[4.761588849],"iteration":204,"passed_time":0.290940341,"remaining_time":1.128280835},
{"learn":[4.758558086],"iteration":205,"passed_time":0.2915470866,"remaining_time":1.123730033},
{"learn":[4.753678804],"iteration":206,"passed_time":0.2922750568,"remaining_time":1.119681739},
{"learn":[4.746510889],"iteration":207,"passed_time":0.293463657,"remaining_time":1.11741931},
{"learn":[4.744840601],"iteration":208,"passed_time":0.2942930088,"remaining_time":1.113807512},
{"learn":[4.741702222],"iteration":209,"passed_time":0.2949968661,"remaining_time":1.109750115},
{"learn":[4.739352853],"iteration":210,"passed_time":0.2956614639,"remaining_time":1.105577701},
{"learn":[4.735539287],"iteration":211,"passed_time":0.2963132929,"remaining_time":1.101390919},
{"learn":[4.730726751],"iteration":212,"passed_time":0.296926936,"remaining_time":1.097096238},
{"learn":[4.726416092],"iteration":213,"passed_time":0.297557701,"remaining_time":1.092898846},
{"learn":[4.721293082],"iteration":214,"passed_time":0.2981683249,"remaining_time":1.088661093},
{"learn":[4.718443695],"iteration":215,"passed_time":0.2988405719,"remaining_time":1.084680594},
{"learn":[4.711627962],"iteration":216,"passed_time":0.2998670926,"remaining_time":1.08200891},
{"learn":[4.709790764],"iteration":217,"passed_time":0.3006175808,"remaining_time":1.078362148},
{"learn":[4.706913073],"iteration":218,"passed_time":0.3013007249,"remaining_time":1.074501672},
{"learn":[4.703846389],"iteration":219,"passed_time":0.3020152242,"remaining_time":1.070781249},
{"learn":[4.701001135],"iteration":220,"passed_time":0.3027812302,"remaining_time":1.067269585},
{"learn":[4.700380864],"iteration":221,"passed_time":0.3034245835,"remaining_time":1.06335282},
{"learn":[4.695837486],"iteration":222,"passed_time":0.304167232,"remaining_time":1.059811387},
{"learn":[4.691242996],"iteration":223,"passed_time":0.3048997864,"remaining_time":1.056259974},
{"learn":[4.690284609],"iteration":224,"passed_time":0.3058236714,"remaining_time":1.053392646},
{"learn":[4.68827119],"iteration":225,"passed_time":0.3066200104,"remaining_time":1.050105699},
{"learn":[4.686922425],"iteration":226,"passed_time":0.3075278166,"remaining_time":1.047220274},
{"learn":[4.686085874],"iteration":227,"passed_time":0.3082003786,"remaining_time":1.043555668},
{"learn":[4.683230741],"iteration":228,"passed_time":0.3088368409,"remaining_time":1.039795652},
{"learn":[4.6773487],"iteration":229,"passed_time":0.30945574,"remaining_time":1.036003999},
{"learn":[4.671462906],"iteration":230,"passed_time":0.3100459118,"remaining_time":1.032144183},
{"learn":[4.664799601],"iteration":231,"passed_time":0.3106483308,"remaining_time":1.028353095},
{"learn":[4.660979386],"iteration":232,"passed_time":0.3114075411,"remaining_time":1.025105511},
{"learn":[4.656281279],"iteration":233,"passed_time":0.3121924843,"remaining_time":1.021963432},
{"learn":[4.651997094],"iteration":234,"passed_time":0.3129863947,"remaining_time":1.018870604},
{"learn":[4.650151977],"iteration":235,"passed_time":0.31372643,"remaining_time":1.01562285},
{"learn":[4.648478046],"iteration":236,"passed_time":0.3146645786,"remaining_time":1.013034065},
{"learn":[4.646364602],"iteration":237,"passed_time":0.3153727487,"remaining_time":1.009722834},
{"learn":[4.642635873],"iteration":238,"passed_time":0.316099134,"remaining_time":1.006491385},
{"learn":[4.640860821],"iteration":239,"passed_time":0.3167952274,"remaining_time":1.003184887},
{"learn":[4.639446822],"iteration":240,"passed_time":0.3175630646,"remaining_time":1.000126},
{"learn":[4.637120072],"iteration":241,"passed_time":0.3185151092,"remaining_time":0.9976630279},
{"learn":[4.633769267],"iteration":242,"passed_time":0.3193694443,"remaining_time":0.9949081042},
{"learn":[4.630491517],"iteration":243,"passed_time":0.320169893,"remaining_time":0.9920017995},
{"learn":[4.627813333],"iteration":244,"passed_time":0.3209684036,"remaining_time":0.989106713},
{"learn":[4.622496304],"iteration":245,"passed_time":0.321798885,"remaining_time":0.9863266637},
{"learn":[4.618979301],"iteration":246,"passed_time":0.3225234248,"remaining_time":0.9832394285},
{"learn":[4.616563458],"iteration":247,"passed_time":0.3232445137,"remaining_time":0.9801607836},
{"learn":[4.614759385],"iteration":248,"passed_time":0.3240599003,"remaining_time":0.9773854824},
{"learn":[4.61251363],"iteration":249,"passed_time":0.3249514261,"remaining_time":0.9748542783},
{"learn":[4.608796693],"iteration":250,"passed_time":0.3258353899,"remaining_time":0.9723135739},
{"learn":[4.60847774],"iteration":251,"passed_time":0.3265969731,"remaining_time":0.9694227614},
{"learn":[4.605195659],"iteration":252,"passed_time":0.3273124544,"remaining_time":0.9664126619},
{"learn":[4.60103766],"iteration":253,"passed_time":0.328043173,"remaining_time":0.963465382},
{"learn":[4.599325598],"iteration":254,"passed_time":0.3288064011,"remaining_time":0.960630466},
{"learn":[4.597012808],"iteration":255,"passed_time":0.3298976342,"remaining_time":0.9587649995},
{"learn":[4.594161533],"iteration":256,"passed_time":0.3309285946,"remaining_time":0.9567313067},
{"learn":[4.592197259],"iteration":257,"passed_time":0.3316845197,"remaining_time":0.9539143939},
{"learn":[4.58952828],"iteration":258,"passed_time":0.3324865447,"remaining_time":0.9512452882},
{"learn":[4.585816572],"iteration":259,"passed_time":0.3331914345,"remaining_time":0.9483140829},
{"learn":[4.582934052],"iteration":260,"passed_time":0.3339064949,"remaining_time":0.9454287346},
{"learn":[4.582234842],"iteration":261,"passed_time":0.3345887422,"remaining_time":0.9424675258},
{"learn":[4.57571562],"iteration":262,"passed_time":0.3352410969,"remaining_time":0.9394398799},
{"learn":[4.571197349],"iteration":263,"passed_time":0.3361317971,"remaining_time":0.937094707},
{"learn":[4.56723703],"iteration":264,"passed_time":0.3370101792,"remaining_time":0.9347263462},
{"learn":[4.560335567],"iteration":265,"passed_time":0.3378755955,"remaining_time":0.9323334101},
{"learn":[4.554709345],"iteration":266,"passed_time":0.3386051906,"remaining_time":0.9295790439},
{"learn":[4.552806306],"iteration":267,"passed_time":0.3393541056,"remaining_time":0.9268925572},
{"learn":[4.550766241],"iteration":268,"passed_time":0.3400403893,"remaining_time":0.9240502771},
{"learn":[4.549216045],"iteration":269,"passed_time":0.3407104825,"remaining_time":0.9211801934},
{"learn":[4.547687452],"iteration":270,"passed_time":0.3415105274,"remaining_time":0.9186759207},
{"learn":[4.545642435],"iteration":271,"passed_time":0.3422794962,"remaining_time":0.9161010044},
{"learn":[4.543930359],"iteration":272,"passed_time":0.3434296281,"remaining_time":0.9145543576},
{"learn":[4.541029943],"iteration":273,"passed_time":0.3442189658,"remaining_time":0.9120546321},
{"learn":[4.537781449],"iteration":274,"passed_time":0.3448137316,"remaining_time":0.9090543833},
{"learn":[4.53066128],"iteration":275,"passed_time":0.3454202832,"remaining_time":0.9061024819},
{"learn":[4.526763956],"iteration":276,"passed_time":0.3460424822,"remaining_time":0.9032083561},
{"learn":[4.522036004],"iteration":277,"passed_time":0.3466460547,"remaining_time":0.9002821997},
{"learn":[4.515307629],"iteration":278,"passed_time":0.3472838311,"remaining_time":0.8974610832},
{"learn":[4.51109143],"iteration":279,"passed_time":0.3478683056,"remaining_time":0.8945185001},
{"learn":[4.508233494],"iteration":280,"passed_time":0.3487483475,"remaining_time":0.8923489745},
{"learn":[4.502555629],"iteration":281,"passed_time":0.3497066852,"remaining_time":0.8903879432},
{"learn":[4.500081355],"iteration":282,"passed_time":0.3504997336,"remaining_time":0.8880152262},
{"learn":[4.495281743],"iteration":283,"passed_time":0.3512856403,"remaining_time":0.8856356285},
{"learn":[4.492138869],"iteration":284,"passed_time":0.3519341693,"remaining_time":0.8829225652},
{"learn":[4.491708261],"iteration":285,"passed_time":0.3526439938,"remaining_time":0.8803769636},
{"learn":[4.489398865],"iteration":286,"passed_time":0.3533407994,"remaining_time":0.8778118117},
{"learn":[4.485796373],"iteration":287,"passed_time":0.3541203462,"remaining_time":0.8754641891},
{"learn":[4.479542205],"iteration":288,"passed_time":0.355060651,"remaining_time":0.8735229165},
{"learn":[4.475986993],"iteration":289,"passed_time":0.3558365279,"remaining_time":0.8711859821},
{"learn":[4.468661855],"iteration":290,"passed_time":0.3566943119,"remaining_time":0.8690593373},
{"learn":[4.463785664],"iteration":291,"passed_time":0.3576128093,"remaining_time":0.8670885924},
{"learn":[4.460445831],"iteration":292,"passed_time":0.3583274089,"remaining_time":0.8646330311},
{"learn":[4.45692492],"iteration":293,"passed_time":0.3590901751,"remaining_time":0.8623049782},
{"learn":[4.454031688],"iteration":294,"passed_time":0.3598661068,"remaining_time":0.860019001},
{"learn":[4.451672391],"iteration":295,"passed_time":0.3606778513,"remaining_time":0.8578284032},
{"learn":[4.45031553],"iteration":296,"passed_time":0.3616310961,"remaining_time":0.8559820221},
{"learn":[4.446782666],"iteration":297,"passed_time":0.3624329494,"remaining_time":0.8537850015},
{"learn":[4.444369689],"iteration":298,"passed_time":0.3632917173,"remaining_time":0.8517307486},
{"learn":[4.44411683],"iteration":299,"passed_time":0.3641250887,"remaining_time":0.8496252071},
{"learn":[4.440876943],"iteration":300,"passed_time":0.3649362161,"remaining_time":0.847476462},
{"learn":[4.439336453],"iteration":301,"passed_time":0.365685806,"remaining_time":0.8451943463},
{"learn":[4.436666901],"iteration":302,"passed_time":0.3665620062,"remaining_time":0.8432135919},
{"learn":[4.433043336],"iteration":303,"passed_time":0.367506375,"remaining_time":0.8413961743},
{"learn":[4.431419305],"iteration":304,"passed_time":0.3685730118,"remaining_time":0.8398630925},
{"learn":[4.428859646],"iteration":305,"passed_time":0.3693891397,"remaining_time":0.8377649115},
{"learn":[4.424552441],"iteration":306,"passed_time":0.3700392435,"remaining_time":0.8353003118},
{"learn":[4.422706391],"iteration":307,"passed_time":0.3709033372,"remaining_time":0.8333282772},
{"learn":[4.421427994],"iteration":308,"passed_time":0.371677356,"remaining_time":0.8311619838},
{"learn":[4.418733158],"iteration":309,"passed_time":0.3724191394,"remaining_time":0.8289329231},
{"learn":[4.415656941],"iteration":310,"passed_time":0.3733138947,"remaining_time":0.8270523262},
{"learn":[4.410747417],"iteration":311,"passed_time":0.3741889113,"remaining_time":0.8251345224},
{"learn":[4.408126521],"iteration":312,"passed_time":0.37506471,"remaining_time":0.8232250983},
{"learn":[4.407843853],"iteration":313,"passed_time":0.375750673,"remaining_time":0.8209075212},
{"learn":[4.405219398],"iteration":314,"passed_time":0.3765739221,"remaining_time":0.8188988466},
{"learn":[4.402708465],"iteration":315,"passed_time":0.3772717709,"remaining_time":0.8166262382},
{"learn":[4.40104971],"iteration":316,"passed_time":0.3781274993,"remaining_time":0.8147037287},
{"learn":[4.400830038],"iteration":317,"passed_time":0.379058116,"remaining_time":0.812948538},
{"learn":[4.39784288],"iteration":318,"passed_time":0.3802008949,"remaining_time":0.8116514403},
{"learn":[4.393741845],"iteration":319,"passed_time":0.3811819974,"remaining_time":0.8100117445},
{"learn":[4.393425936],"iteration":320,"passed_time":0.3819525723,"remaining_time":0.8079308304},
{"learn":[4.390505974],"iteration":321,"passed_time":0.3827436487,"remaining_time":0.8059012231},
{"learn":[4.390305136],"iteration":322,"passed_time":0.383454176,"remaining_time":0.8037104555},
{"learn":[4.38568203],"iteration":323,"passed_time":0.3842522756,"remaining_time":0.801711538},
{"learn":[4.383057135],"iteration":324,"passed_time":0.3852138751,"remaining_time":0.8000595868},
{"learn":[4.380662684],"iteration":325,"passed_time":0.3865070413,"remaining_time":0.7990973799},
{"learn":[4.37805727],"iteration":326,"passed_time":0.3874375148,"remaining_time":0.7973866894},
{"learn":[4.373708319],"iteration":327,"passed_time":0.388257867,"remaining_time":0.7954551422},
{"learn":[4.36887921],"iteration":328,"passed_time":0.3891518503,"remaining_time":0.7936805214},
{"learn":[4.367895929],"iteration":329,"passed_time":0.3899547386,"remaining_time":0.7917262874},
{"learn":[4.362140573],"iteration":330,"passed_time":0.3906887565,"remaining_time":0.789639813},
{"learn":[4.361931924],"iteration":331,"passed_time":0.3916644027,"remaining_time":0.7880476537},
{"learn":[4.359656377],"iteration":332,"passed_time":0.3926519607,"remaining_time":0.7864830565},
{"learn":[4.354281355],"iteration":333,"passed_time":0.393423008,"remaining_time":0.7844901895},
{"learn":[4.348589447],"iteration":334,"passed_time":0.3941791537,"remaining_time":0.7824750364},
{"learn":[4.346355698],"iteration":335,"passed_time":0.3948560087,"remaining_time":0.7803106838},
{"learn":[4.343894047],"iteration":336,"passed_time":0.3954573544,"remaining_time":0.7780066053},
{"learn":[4.341561356],"iteration":337,"passed_time":0.3960627224,"remaining_time":0.7757204799},
{"learn":[4.338869061],"iteration":338,"passed_time":0.3966015383,"remaining_time":0.7733145039},
{"learn":[4.333720063],"iteration":339,"passed_time":0.3972168217,"remaining_time":0.7710679479},
{"learn":[4.330892223],"iteration":340,"passed_time":0.3981221691,"remaining_time":0.7693915233},
{"learn":[4.328311474],"iteration":341,"passed_time":0.3991323073,"remaining_time":0.7679212227},
{"learn":[4.324580133],"iteration":342,"passed_time":0.3999829602,"remaining_time":0.7661481192},
{"learn":[4.323354432],"iteration":343,"passed_time":0.4010225967,"remaining_time":0.7647407658},
{"learn":[4.323159553],"iteration":344,"passed_time":0.4017720016,"remaining_time":0.7627845248},
{"learn":[4.318639682],"iteration":345,"passed_time":0.4025046673,"remaining_time":0.7608036198},
{"learn":[4.312712208],"iteration":346,"passed_time":0.4031667074,"remaining_time":0.7586970026},
{"learn":[4.311461062],"iteration":347,"passed_time":0.4040346525,"remaining_time":0.7569844639},
{"learn":[4.311178356],"iteration":348,"passed_time":0.4047553807,"remaining_time":0.7550021572},
{"learn":[4.311102505],"iteration":349,"passed_time":0.4054018134,"remaining_time":0.7528890819},
{"learn":[4.310232308],"iteration":350,"passed_time":0.4060290477,"remaining_time":0.750748866},
{"learn":[4.305128197],"iteration":351,"passed_time":0.4067518422,"remaining_time":0.748793164},
{"learn":[4.304595496],"iteration":352,"passed_time":0.4073328662,"remaining_time":0.7465846018},
{"learn":[4.3004992],"iteration":353,"passed_time":0.4079240912,"remaining_time":0.7444038501},
{"learn":[4.297581524],"iteration":354,"passed_time":0.4085385267,"remaining_time":0.7422742246},
{"learn":[4.297355825],"iteration":355,"passed_time":0.4091324098,"remaining_time":0.7401159324},
{"learn":[4.295758715],"iteration":356,"passed_time":0.4099801232,"remaining_time":0.7384235833},
{"learn":[4.292500657],"iteration":357,"passed_time":0.4108674563,"remaining_time":0.7368070027},
{"learn":[4.290797586],"iteration":358,"passed_time":0.4114959144,"remaining_time":0.7347322594},
{"learn":[4.286410608],"iteration":359,"passed_time":0.4122084678,"remaining_time":0.7328150538},
{"learn":[4.280278245],"iteration":360,"passed_time":0.4128895672,"remaining_time":0.7308488462},
{"learn":[4.279941283],"iteration":361,"passed_time":0.4137559069,"remaining_time":0.7292162116},
{"learn":[4.274426275],"iteration":362,"passed_time":0.4144255701,"remaining_time":0.727242667},
{"learn":[4.273567658],"iteration":363,"passed_time":0.415106578,"remaining_time":0.7252961088},
{"learn":[4.269488271],"iteration":364,"passed_time":0.4157822629,"remaining_time":0.7233472244},
{"learn":[4.266838205],"iteration":365,"passed_time":0.4165762635,"remaining_time":0.7216102489},
{"learn":[4.263456509],"iteration":366,"passed_time":0.4174686996,"remaining_time":0.7200481931},
{"learn":[4.260360204],"iteration":367,"passed_time":0.4182727405,"remaining_time":0.7183379673},
{"learn":[4.255120549],"iteration":368,"passed_time":0.4190922987,"remaining_time":0.7166591883},
{"learn":[4.252582211],"iteration":369,"passed_time":0.4198572311,"remaining_time":0.7148920422},
{"learn":[4.247857931],"iteration":370,"passed_time":0.420510986,"remaining_time":0.7129418064},
{"learn":[4.245288911],"iteration":371,"passed_time":0.4212926097,"remaining_time":0.7112144056},
{"learn":[4.24048515],"iteration":372,"passed_time":0.4220593862,"remaining_time":0.7094671183},
{"learn":[4.2378365],"iteration":373,"passed_time":0.4230130879,"remaining_time":0.7080379493},
{"learn":[4.236751063],"iteration":374,"passed_time":0.4236722592,"remaining_time":0.7061204321},
{"learn":[4.233240093],"iteration":375,"passed_time":0.4243817233,"remaining_time":0.7042930726},
{"learn":[4.230358421],"iteration":376,"passed_time":0.4250604138,"remaining_time":0.70242079},
{"learn":[4.225853583],"iteration":377,"passed_time":0.4257525888,"remaining_time":0.7005770112},
{"learn":[4.224702126],"iteration":378,"passed_time":0.4264306976,"remaining_time":0.6987162617},
{"learn":[4.224361982],"iteration":379,"passed_time":0.4270231062,"remaining_time":0.6967219101},
{"learn":[4.223787954],"iteration":380,"passed_time":0.4276363681,"remaining_time":0.6947687975},
{"learn":[4.22144054],"iteration":381,"passed_time":0.4282987705,"remaining_time":0.6929021994},
{"learn":[4.217739335],"iteration":382,"passed_time":0.4291813495,"remaining_time":0.6913965865},
{"learn":[4.215611665],"iteration":383,"passed_time":0.4299235729,"remaining_time":0.6896690649},
{"learn":[4.210236863],"iteration":384,"passed_time":0.4306594731,"remaining_time":0.687936561},
{"learn":[4.208454294],"iteration":385,"passed_time":0.4313304703,"remaining_time":0.6861059813},
{"learn":[4.207446501],"iteration":386,"passed_time":0.4318564773,"remaining_time":0.6840517329},
{"learn":[4.204985442],"iteration":387,"passed_time":0.4324326567,"remaining_time":0.6820844997},
{"learn":[4.202796622],"iteration":388,"passed_time":0.4331016879,"remaining_time":0.6802702605},
{"learn":[4.199774004],"iteration":389,"passed_time":0.4337445096,"remaining_time":0.6784208996},
{"learn":[4.199458358],"iteration":390,"passed_time":0.4343941761,"remaining_time":0.6765883715},
{"learn":[4.19751254],"iteration":391,"passed_time":0.435178136,"remaining_time":0.6749701701},
{"learn":[4.195201346],"iteration":392,"passed_time":0.4359147625,"remaining_time":0.6732831064},
{"learn":[4.190593508],"iteration":393,"passed_time":0.4365449959,"remaining_time":0.6714372272},
{"learn":[4.187212054],"iteration":394,"passed_time":0.4371812777,"remaining_time":0.6696067671},
{"learn":[4.184984466],"iteration":395,"passed_time":0.4377932557,"remaining_time":0.6677452689},
{"learn":[4.182832144],"iteration":396,"passed_time":0.4383691442,"remaining_time":0.6658352493},
{"learn":[4.179752812],"iteration":397,"passed_time":0.4390060981,"remaining_time":0.6640242991},
{"learn":[4.17878934],"iteration":398,"passed_time":0.4396420091,"remaining_time":0.6622176628},
{"learn":[4.174548229],"iteration":399,"passed_time":0.4402819219,"remaining_time":0.6604228828},
{"learn":[4.168872556],"iteration":400,"passed_time":0.4412389381,"remaining_time":0.659107541},
{"learn":[4.163926494],"iteration":401,"passed_time":0.4418630718,"remaining_time":0.6572987984},
{"learn":[4.159485076],"iteration":402,"passed_time":0.4425599993,"remaining_time":0.6556037707},
{"learn":[4.155926102],"iteration":403,"passed_time":0.4432448085,"remaining_time":0.6538958065},
{"learn":[4.153540115],"iteration":404,"passed_time":0.4438810301,"remaining_time":0.6521215133},
{"learn":[4.150983044],"iteration":405,"passed_time":0.4445067799,"remaining_time":0.6503375056},
{"learn":[4.146539132],"iteration":406,"passed_time":0.4451551484,"remaining_time":0.648592145},
{"learn":[4.144869174],"iteration":407,"passed_time":0.4457560027,"remaining_time":0.6467832196},
{"learn":[4.142825962],"iteration":408,"passed_time":0.4463980821,"remaining_time":0.6450397715},
{"learn":[4.142467378],"iteration":409,"passed_time":0.447110234,"remaining_time":0.6434025318},
{"learn":[4.141800768],"iteration":410,"passed_time":0.4478810179,"remaining_time":0.6418538188},
{"learn":[4.140107084],"iteration":411,"passed_time":0.4485450941,"remaining_time":0.6401565906},
{"learn":[4.136243196],"iteration":412,"passed_time":0.4491962009,"remaining_time":0.638445932},
{"learn":[4.133618439],"iteration":413,"passed_time":0.4499147926,"remaining_time":0.6368359142},
{"learn":[4.131053025],"iteration":414,"passed_time":0.4505411744,"remaining_time":0.6351002097},
{"learn":[4.128379975],"iteration":415,"passed_time":0.4511780881,"remaining_time":0.6333846237},
{"learn":[4.127068571],"iteration":416,"passed_time":0.4518447588,"remaining_time":0.6317158138},
{"learn":[4.125969877],"iteration":417,"passed_time":0.4524355324,"remaining_time":0.6299461241},
{"learn":[4.123893633],"iteration":418,"passed_time":0.4530651427,"remaining_time":0.6282359139},
{"learn":[4.119643722],"iteration":419,"passed_time":0.4539761433,"remaining_time":0.626919436},
{"learn":[4.11465686],"iteration":420,"passed_time":0.4547139534,"remaining_time":0.6253666959},
{"learn":[4.111565986],"iteration":421,"passed_time":0.4554254993,"remaining_time":0.623781845},
{"learn":[4.106322452],"iteration":422,"passed_time":0.4560872484,"remaining_time":0.622133197},
{"learn":[4.104222175],"iteration":423,"passed_time":0.4567627192,"remaining_time":0.620507845},
{"learn":[4.103008002],"iteration":424,"passed_time":0.4573848782,"remaining_time":0.6188148352},
{"learn":[4.099176337],"iteration":425,"passed_time":0.4580352728,"remaining_time":0.6171648981},
{"learn":[4.096525716],"iteration":426,"passed_time":0.4586476822,"remaining_time":0.6154686695},
{"learn":[4.094967724],"iteration":427,"passed_time":0.4593822336,"remaining_time":0.6139407421},
{"learn":[4.094683584],"iteration":428,"passed_time":0.4602152214,"remaining_time":0.6125475324},
{"learn":[4.091096563],"iteration":429,"passed_time":0.460953533,"remaining_time":0.6110314274},
{"learn":[4.089178677],"iteration":430,"passed_time":0.4615734952,"remaining_time":0.6093626886},
{"learn":[4.085335077],"iteration":431,"passed_time":0.4621602166,"remaining_time":0.6076550996},
{"learn":[4.084852122],"iteration":432,"passed_time":0.4627541298,"remaining_time":0.6059621052},
{"learn":[4.080322952],"iteration":433,"passed_time":0.4633469596,"remaining_time":0.604272763},
{"learn":[4.077449519],"iteration":434,"passed_time":0.4639434908,"remaining_time":0.6025932696},
{"learn":[4.076568374],"iteration":435,"passed_time":0.4645255279,"remaining_time":0.6008999948},
{"learn":[4.076071793],"iteration":436,"passed_time":0.4650793794,"remaining_time":0.5991754934},
{"learn":[4.075027644],"iteration":437,"passed_time":0.4658266589,"remaining_time":0.5977045258},
{"learn":[4.07020837],"iteration":438,"passed_time":0.4665600054,"remaining_time":0.5962190502},
{"learn":[4.06833694],"iteration":439,"passed_time":0.4672477535,"remaining_time":0.594678959},
{"learn":[4.063936568],"iteration":440,"passed_time":0.4681436237,"remaining_time":0.5934065435},
{"learn":[4.061734926],"iteration":441,"passed_time":0.4688178307,"remaining_time":0.5918559944},
{"learn":[4.060815619],"iteration":442,"passed_time":0.4693405979,"remaining_time":0.590118991},
{"learn":[4.056407489],"iteration":443,"passed_time":0.4699107589,"remaining_time":0.5884468062},
{"learn":[4.05238936],"iteration":444,"passed_time":0.4705327674,"remaining_time":0.586844238},
{"learn":[4.049685254],"iteration":445,"passed_time":0.4711339025,"remaining_time":0.585220139},
{"learn":[4.045162016],"iteration":446,"passed_time":0.4717450878,"remaining_time":0.5836130505},
{"learn":[4.042955482],"iteration":447,"passed_time":0.4726549001,"remaining_time":0.5823783591},
{"learn":[4.041467663],"iteration":448,"passed_time":0.4733718167,"remaining_time":0.5809083987},
{"learn":[4.038920476],"iteration":449,"passed_time":0.4742544556,"remaining_time":0.5796443346},
{"learn":[4.036694383],"iteration":450,"passed_time":0.4750832629,"remaining_time":0.5783164331},
{"learn":[4.034999007],"iteration":451,"passed_time":0.4758531393,"remaining_time":0.5769192928},
{"learn":[4.031928018],"iteration":452,"passed_time":0.4767342357,"remaining_time":0.5756592206},
{"learn":[4.028718143],"iteration":453,"passed_time":0.4775754384,"remaining_time":0.57435284},
{"learn":[4.027401978],"iteration":454,"passed_time":0.478430449,"remaining_time":0.5730650433},
{"learn":[4.025930598],"iteration":455,"passed_time":0.4792585918,"remaining_time":0.5717470919},
{"learn":[4.021074523],"iteration":456,"passed_time":0.480143237,"remaining_time":0.5704984195},
{"learn":[4.020268486],"iteration":457,"passed_time":0.4809866781,"remaining_time":0.5692025754},
{"learn":[4.017986361],"iteration":458,"passed_time":0.4819127093,"remaining_time":0.5680060473},
{"learn":[4.014814804],"iteration":459,"passed_time":0.4827671735,"remaining_time":0.566726682},
{"learn":[4.009704796],"iteration":460,"passed_time":0.4835485597,"remaining_time":0.5653637173},
{"learn":[4.008440457],"iteration":461,"passed_time":0.4846539006,"remaining_time":0.5643805163},
{"learn":[4.004854849],"iteration":462,"passed_time":0.485488744,"remaining_time":0.5630830573},
{"learn":[4.000898028],"iteration":463,"passed_time":0.4863003795,"remaining_time":0.5617607832},
{"learn":[3.996617985],"iteration":464,"passed_time":0.4872721787,"remaining_time":0.5606249798},
{"learn":[3.995443319],"iteration":465,"passed_time":0.488107224,"remaining_time":0.5593331708},
{"learn":[3.990771995],"iteration":466,"passed_time":0.4888159858,"remaining_time":0.5578991873},
{"learn":[3.989249359],"iteration":467,"passed_time":0.4897971648,"remaining_time":0.5567779736},
{"learn":[3.986599538],"iteration":468,"passed_time":0.4909495347,"remaining_time":0.555851179},
{"learn":[3.985628919],"iteration":469,"passed_time":0.4917867265,"remaining_time":0.5545680108},
{"learn":[3.985086112],"iteration":470,"passed_time":0.4924724068,"remaining_time":0.5531165673},
{"learn":[3.98466839],"iteration":471,"passed_time":0.4932380717,"remaining_time":0.5517578429},
{"learn":[3.984233894],"iteration":472,"passed_time":0.4940314301,"remaining_time":0.5504324813},
{"learn":[3.981855845],"iteration":473,"passed_time":0.4946902805,"remaining_time":0.5489601003},
{"learn":[3.978684264],"iteration":474,"passed_time":0.495631709,"remaining_time":0.5478034679},
{"learn":[3.974361269],"iteration":475,"passed_time":0.4965678312,"remaining_time":0.5466418982},
{"learn":[3.972074049],"iteration":476,"passed_time":0.4975381625,"remaining_time":0.545518782},
{"learn":[3.97191982],"iteration":477,"passed_time":0.4983811203,"remaining_time":0.5442572067},
{"learn":[3.969616848],"iteration":478,"passed_time":0.4991249148,"remaining_time":0.5428895211},
{"learn":[3.968533527],"iteration":479,"passed_time":0.4998545741,"remaining_time":0.541509122},
{"learn":[3.967568753],"iteration":480,"passed_time":0.5005221309,"remaining_time":0.5400644198},
{"learn":[3.966232553],"iteration":481,"passed_time":0.5012370574,"remaining_time":0.5386738501},
{"learn":[3.961522393],"iteration":482,"passed_time":0.5019026222,"remaining_time":0.5372332416},
{"learn":[3.955829553],"iteration":483,"passed_time":0.5026572192,"remaining_time":0.5358907543},
{"learn":[3.954248095],"iteration":484,"passed_time":0.5035800711,"remaining_time":0.5347293538},
{"learn":[3.951922606],"iteration":485,"passed_time":0.5045768214,"remaining_time":0.5336470909},
{"learn":[3.94978202],"iteration":486,"passed_time":0.5054300277,"remaining_time":0.5324139717},
{"learn":[3.949518999],"iteration":487,"passed_time":0.5062236811,"remaining_time":0.5311199277},
{"learn":[3.945431216],"iteration":488,"passed_time":0.5068531121,"remaining_time":0.5296563196},
{"learn":[3.943249086],"iteration":489,"passed_time":0.5075743218,"remaining_time":0.528291641},
{"learn":[3.941981548],"iteration":490,"passed_time":0.5082983603,"remaining_time":0.5269325161},
{"learn":[3.936600517],"iteration":491,"passed_time":0.509264945,"remaining_time":0.5258264066},
{"learn":[3.934476885],"iteration":492,"passed_time":0.5102797275,"remaining_time":0.5247704297},
{"learn":[3.93045798],"iteration":493,"passed_time":0.5112363115,"remaining_time":0.5236550073},
{"learn":[3.925977375],"iteration":494,"passed_time":0.5119649938,"remaining_time":0.522307721},
{"learn":[3.92457993],"iteration":495,"passed_time":0.5126496024,"remaining_time":0.5209181443},
{"learn":[3.919849146],"iteration":496,"passed_time":0.513329296,"remaining_time":0.5195264304},
{"learn":[3.919681964],"iteration":497,"passed_time":0.5139319357,"remaining_time":0.518059903},
{"learn":[3.917633027],"iteration":498,"passed_time":0.5146073162,"remaining_time":0.5166698706},
{"learn":[3.916616419],"iteration":499,"passed_time":0.515451498,"remaining_time":0.515451498},
{"learn":[3.912896166],"iteration":500,"passed_time":0.5163301469,"remaining_time":0.5142689487},
{"learn":[3.912769674],"iteration":501,"passed_time":0.517044927,"remaining_time":0.5129250471},
{"learn":[3.909373788],"iteration":502,"passed_time":0.5177484831,"remaining_time":0.5115725568},
{"learn":[3.906706036],"iteration":503,"passed_time":0.5183821971,"remaining_time":0.5101539083},
{"learn":[3.903895664],"iteration":504,"passed_time":0.5190150084,"remaining_time":0.5087374835},
{"learn":[3.902982967],"iteration":505,"passed_time":0.5196327038,"remaining_time":0.5073093985},
{"learn":[3.900905528],"iteration":506,"passed_time":0.5202995985,"remaining_time":0.5059323512},
{"learn":[3.897463465],"iteration":507,"passed_time":0.520989573,"remaining_time":0.5045804526},
{"learn":[3.895918033],"iteration":508,"passed_time":0.5218761448,"remaining_time":0.5034207998},
{"learn":[3.893921936],"iteration":509,"passed_time":0.5227889461,"remaining_time":0.5022874188},
{"learn":[3.890237934],"iteration":510,"passed_time":0.5236327016,"remaining_time":0.5010888279},
{"learn":[3.887311613],"iteration":511,"passed_time":0.5244778441,"remaining_time":0.4998929452},
{"learn":[3.884869735],"iteration":512,"passed_time":0.5255842533,"remaining_time":0.4989464549},
{"learn":[3.882101231],"iteration":513,"passed_time":0.5262932559,"remaining_time":0.4976235843},
{"learn":[3.88060368],"iteration":514,"passed_time":0.5269621266,"remaining_time":0.4962653037},
{"learn":[3.877726076],"iteration":515,"passed_time":0.5278435715,"remaining_time":0.4951090865},
{"learn":[3.874938145],"iteration":516,"passed_time":0.5285698579,"remaining_time":0.4938089775},
{"learn":[3.874340833],"iteration":517,"passed_time":0.5293927663,"remaining_time":0.492600991},
{"learn":[3.873105224],"iteration":518,"passed_time":0.5301589613,"remaining_time":0.4913419275},
{"learn":[3.869800236],"iteration":519,"passed_time":0.5308613037,"remaining_time":0.4900258188},
{"learn":[3.867932518],"iteration":520,"passed_time":0.5315203345,"remaining_time":0.4886722462},
{"learn":[3.866666962],"iteration":521,"passed_time":0.5321865974,"remaining_time":0.487327957},
{"learn":[3.865527652],"iteration":522,"passed_time":0.5328322276,"remaining_time":0.4859674427},
{"learn":[3.861900081],"iteration":523,"passed_time":0.5333466093,"remaining_time":0.4844904313},
{"learn":[3.858502887],"iteration":524,"passed_time":0.5341957583,"remaining_time":0.4833199718},
{"learn":[3.858335097],"iteration":525,"passed_time":0.5349436189,"remaining_time":0.4820594589},
{"learn":[3.855719306],"iteration":526,"passed_time":0.5356874426,"remaining_time":0.4807972682},
{"learn":[3.855137428],"iteration":527,"passed_time":0.5362986482,"remaining_time":0.4794184886},
{"learn":[3.851985706],"iteration":528,"passed_time":0.5369051296,"remaining_time":0.4780384046},
{"learn":[3.851051809],"iteration":529,"passed_time":0.5375276998,"remaining_time":0.4766755073},
{"learn":[3.850679146],"iteration":530,"passed_time":0.5381560074,"remaining_time":0.475320466},
{"learn":[3.848179484],"iteration":531,"passed_time":0.5387403916,"remaining_time":0.4739295174},
{"learn":[3.844551071],"iteration":532,"passed_time":0.5393436732,"remaining_time":0.4725581527},
{"learn":[3.841604794],"iteration":533,"passed_time":0.5402395886,"remaining_time":0.4714450343},
{"learn":[3.83969656],"iteration":534,"passed_time":0.5410967805,"remaining_time":0.4702990709},
{"learn":[3.836811463],"iteration":535,"passed_time":0.5417525515,"remaining_time":0.4689798207},
{"learn":[3.834182551],"iteration":536,"passed_time":0.5423294831,"remaining_time":0.4675950665},
{"learn":[3.828012842],"iteration":537,"passed_time":0.5430010173,"remaining_time":0.4662945539},
{"learn":[3.826636176],"iteration":538,"passed_time":0.5436190437,"remaining_time":0.4649506106},
{"learn":[3.826189798],"iteration":539,"passed_time":0.544188964,"remaining_time":0.4635683768},
{"learn":[3.824104738],"iteration":540,"passed_time":0.5448205115,"remaining_time":0.4622414321},
{"learn":[3.82300218],"iteration":541,"passed_time":0.5454502133,"remaining_time":0.4609154939},
{"learn":[3.817146402],"iteration":542,"passed_time":0.5462755544,"remaining_time":0.4597567742},
{"learn":[3.814638044],"iteration":543,"passed_time":0.5470683602,"remaining_time":0.4585720078},
{"learn":[3.812979573],"iteration":544,"passed_time":0.5477526478,"remaining_time":0.4572980821},
{"learn":[3.811938825],"iteration":545,"passed_time":0.5484136145,"remaining_time":0.4560069249},
{"learn":[3.811479418],"iteration":546,"passed_time":0.5490535575,"remaining_time":0.4547006609},
{"learn":[3.80742981],"iteration":547,"passed_time":0.5497002409,"remaining_time":0.4534023884},
{"learn":[3.805097043],"iteration":548,"passed_time":0.5503818964,"remaining_time":0.4521352191},
{"learn":[3.801577232],"iteration":549,"passed_time":0.5509998325,"remaining_time":0.4508180448},
{"learn":[3.799762083],"iteration":550,"passed_time":0.5515382773,"remaining_time":0.4494386325},
{"learn":[3.796393455],"iteration":551,"passed_time":0.5521264784,"remaining_time":0.4481026491},
{"learn":[3.793486459],"iteration":552,"passed_time":0.5529940966,"remaining_time":0.4469952282},
{"learn":[3.792006091],"iteration":553,"passed_time":0.553717824,"remaining_time":0.445772833},
{"learn":[3.78932128],"iteration":554,"passed_time":0.5544587936,"remaining_time":0.4445660597},
{"learn":[3.787581812],"iteration":555,"passed_time":0.5551405635,"remaining_time":0.4433136874},
{"learn":[3.785308865],"iteration":556,"passed_time":0.5557793831,"remaining_time":0.4420292041},
{"learn":[3.78465475],"iteration":557,"passed_time":0.5563448499,"remaining_time":0.4406889313},
{"learn":[3.780498869],"iteration":558,"passed_time":0.5568741469,"remaining_time":0.4393228958},
{"learn":[3.778734909],"iteration":559,"passed_time":0.5573806346,"remaining_time":0.4379419272},
{"learn":[3.778652349],"iteration":560,"passed_time":0.5580277393,"remaining_time":0.4366741133},
{"learn":[3.777928006],"iteration":561,"passed_time":0.5589199942,"remaining_time":0.4355995684},
{"learn":[3.776131406],"iteration":562,"passed_time":0.5596668881,"remaining_time":0.4344128421},
{"learn":[3.772925617],"iteration":563,"passed_time":0.5602826777,"remaining_time":0.4331263253},
{"learn":[3.7727745],"iteration":564,"passed_time":0.5608829502,"remaining_time":0.431830236},
{"learn":[3.771763073],"iteration":565,"passed_time":0.5615230235,"remaining_time":0.430567124},
{"learn":[3.768738162],"iteration":566,"passed_time":0.5621395754,"remaining_time":0.4292882472},
{"learn":[3.767220794],"iteration":567,"passed_time":0.5627811633,"remaining_time":0.428030744},
{"learn":[3.766691102],"iteration":568,"passed_time":0.5632890854,"remaining_time":0.4266741579},
{"learn":[3.766259335],"iteration":569,"passed_time":0.5638111505,"remaining_time":0.4253312188},
{"learn":[3.76116362],"iteration":570,"passed_time":0.5645733587,"remaining_time":0.4241715777},
{"learn":[3.758633056],"iteration":571,"passed_time":0.5657915933,"remaining_time":0.4233545488},
{"learn":[3.754603809],"iteration":572,"passed_time":0.5666094401,"remaining_time":0.4222377503},
{"learn":[3.754070549],"iteration":573,"passed_time":0.5674097214,"remaining_time":0.421108957},
{"learn":[3.750534319],"iteration":574,"passed_time":0.5681084024,"remaining_time":0.4199062104},
{"learn":[3.746491516],"iteration":575,"passed_time":0.5687739831,"remaining_time":0.4186808487},
{"learn":[3.744210544],"iteration":576,"passed_time":0.5693828517,"remaining_time":0.4174158514},
{"learn":[3.742929991],"iteration":577,"passed_time":0.5699738059,"remaining_time":0.4161400452},
{"learn":[3.740402992],"iteration":578,"passed_time":0.5706090747,"remaining_time":0.4148988263},
{"learn":[3.739644243],"iteration":579,"passed_time":0.5714466363,"remaining_time":0.4138061849},
{"learn":[3.737529404],"iteration":580,"passed_time":0.5722398158,"remaining_time":0.4126824145},
{"learn":[3.737196923],"iteration":581,"passed_time":0.5729914879,"remaining_time":0.411529969},
{"learn":[3.733954464],"iteration":582,"passed_time":0.5736847628,"remaining_time":0.4103371288},
{"learn":[3.731608623],"iteration":583,"passed_time":0.5743582375,"remaining_time":0.4091318952},
{"learn":[3.729843952],"iteration":584,"passed_time":0.5749989227,"remaining_time":0.4079052187},
{"learn":[3.727223798],"iteration":585,"passed_time":0.5756320148,"remaining_time":0.4066751777},
{"learn":[3.725351667],"iteration":586,"passed_time":0.5762525388,"remaining_time":0.405438328},
{"learn":[3.725026912],"iteration":587,"passed_time":0.5768977276,"remaining_time":0.4042208568},
{"learn":[3.721974565],"iteration":588,"passed_time":0.5777383937,"remaining_time":0.4031417315},
{"learn":[3.720269493],"iteration":589,"passed_time":0.5785904469,"remaining_time":0.4020713275},
{"learn":[3.718907466],"iteration":590,"passed_time":0.5796635142,"remaining_time":0.4011546147},
{"learn":[3.715602912],"iteration":591,"passed_time":0.5803568091,"remaining_time":0.3999756387},
{"learn":[3.714463059],"iteration":592,"passed_time":0.5810267531,"remaining_time":0.3987822741},
{"learn":[3.710802077],"iteration":593,"passed_time":0.5816311281,"remaining_time":0.3975458552},
{"learn":[3.708032435],"iteration":594,"passed_time":0.5822238476,"remaining_time":0.3963036274},
{"learn":[3.703788939],"iteration":595,"passed_time":0.5828486646,"remaining_time":0.3950853364},
{"learn":[3.702500944],"iteration":596,"passed_time":0.5836434678,"remaining_time":0.3939837814},
{"learn":[3.698196925],"iteration":597,"passed_time":0.5845055658,"remaining_time":0.3929284907},
{"learn":[3.69658891],"iteration":598,"passed_time":0.5852235858,"remaining_time":0.3917773921},
{"learn":[3.696124066],"iteration":599,"passed_time":0.5861747442,"remaining_time":0.3907831628},
{"learn":[3.693537052],"iteration":600,"passed_time":0.5869214212,"remaining_time":0.3896533229},
{"learn":[3.691343275],"iteration":601,"passed_time":0.5875744438,"remaining_time":0.3884628383},
{"learn":[3.690973831],"iteration":602,"passed_time":0.5882477669,"remaining_time":0.3872875016},
{"learn":[3.686151073],"iteration":603,"passed_time":0.5889192656,"remaining_time":0.3861126311},
{"learn":[3.683921982],"iteration":604,"passed_time":0.5898248162,"remaining_time":0.3850922354},
{"learn":[3.679975271],"iteration":605,"passed_time":0.5906214335,"remaining_time":0.3840013941},
{"learn":[3.674047638],"iteration":606,"passed_time":0.5913575083,"remaining_time":0.3828723242},
{"learn":[3.673151794],"iteration":607,"passed_time":0.5920416856,"remaining_time":0.3817110868},
{"learn":[3.670953108],"iteration":608,"passed_time":0.5926495812,"remaining_time":0.3805024405},
{"learn":[3.6703947],"iteration":609,"passed_time":0.5933274092,"remaining_time":0.3793404747},
{"learn":[3.668433805],"iteration":610,"passed_time":0.5940093496,"remaining_time":0.3781827119},
{"learn":[3.668304956],"iteration":611,"passed_time":0.5946583701,"remaining_time":0.3770056333},
{"learn":[3.667880012],"iteration":612,"passed_time":0.5952809002,"remaining_time":0.3758135536},
{"learn":[3.667282264],"iteration":613,"passed_time":0.5960766072,"remaining_time":0.3747321993},
{"learn":[3.664611483],"iteration":614,"passed_time":0.5968925433,"remaining_time":0.3736644377},
{"learn":[3.662543394],"iteration":615,"passed_time":0.5977317926,"remaining_time":0.3726120265},
{"learn":[3.659041959],"iteration":616,"passed_time":0.5984784796,"remaining_time":0.3715028487},
{"learn":[3.656868545],"iteration":617,"passed_time":0.5991916749,"remaining_time":0.3703741421},
{"learn":[3.654785614],"iteration":618,"passed_time":0.5998299728,"remaining_time":0.369200678},
{"learn":[3.654566096],"iteration":619,"passed_time":0.6004966971,"remaining_time":0.3680463627},
{"learn":[3.651007045],"iteration":620,"passed_time":0.601138947,"remaining_time":0.366878681},
{"learn":[3.648921786],"iteration":621,"passed_time":0.6018196336,"remaining_time":0.3657360475},
{"learn":[3.647655706],"iteration":622,"passed_time":0.6026695193,"remaining_time":0.3646972854},
{"learn":[3.647241144],"iteration":623,"passed_time":0.6034004786,"remaining_time":0.3635874679},
{"learn":[3.644195689],"iteration":624,"passed_time":0.60412557,"remaining_time":0.362475342},
{"learn":[3.642632246],"iteration":625,"passed_time":0.6048477235,"remaining_time":0.3613626974},
{"learn":[3.642523322],"iteration":626,"passed_time":0.6054151049,"remaining_time":0.3601592251},
{"learn":[3.641494659],"iteration":627,"passed_time":0.6061065288,"remaining_time":0.3590312559},
{"learn":[3.63976496],"iteration":628,"passed_time":0.6068601722,"remaining_time":0.3579413734},
{"learn":[3.637945652],"iteration":629,"passed_time":0.6076207113,"remaining_time":0.3568566082},
{"learn":[3.636233667],"iteration":630,"passed_time":0.6086196351,"remaining_time":0.3559122747},
{"learn":[3.635304404],"iteration":631,"passed_time":0.6095431489,"remaining_time":0.3549238589},
{"learn":[3.632234951],"iteration":632,"passed_time":0.6103062345,"remaining_time":0.3538426352},
{"learn":[3.631630987],"iteration":633,"passed_time":0.6111128945,"remaining_time":0.35278757},
{"learn":[3.630301009],"iteration":634,"passed_time":0.611736879,"remaining_time":0.3516282848},
{"learn":[3.629077964],"iteration":635,"passed_time":0.61233665,"remaining_time":0.3504568248},
{"learn":[3.628004522],"iteration":636,"passed_time":0.6129304629,"remaining_time":0.3492837645},
{"learn":[3.625062876],"iteration":637,"passed_time":0.6135211964,"remaining_time":0.3481107729},
{"learn":[3.624917986],"iteration":638,"passed_time":0.6141217284,"remaining_time":0.3469451392},
{"learn":[3.622887087],"iteration":639,"passed_time":0.6149455506,"remaining_time":0.3459068722},
{"learn":[3.621220865],"iteration":640,"passed_time":0.6156923078,"remaining_time":0.3448261131},
{"learn":[3.621143844],"iteration":641,"passed_time":0.6163534451,"remaining_time":0.34369865},
{"learn":[3.620822821],"iteration":642,"passed_time":0.6169115395,"remaining_time":0.3425154271},
{"learn":[3.619202826],"iteration":643,"passed_time":0.617510498,"remaining_time":0.3413567349},
{"learn":[3.618204882],"iteration":644,"passed_time":0.618128745,"remaining_time":0.3402103946},
{"learn":[3.614259666],"iteration":645,"passed_time":0.6187569925,"remaining_time":0.3390711692},
{"learn":[3.613415661],"iteration":646,"passed_time":0.6193687799,"remaining_time":0.337924543},
{"learn":[3.611096773],"iteration":647,"passed_time":0.6200332072,"remaining_time":0.3368081619},
{"learn":[3.610820695],"iteration":648,"passed_time":0.6208544609,"remaining_time":0.3357779904},
{"learn":[3.609290065],"iteration":649,"passed_time":0.6215593908,"remaining_time":0.3346858258},
{"learn":[3.60897947],"iteration":650,"passed_time":0.622341034,"remaining_time":0.3336359767},
{"learn":[3.606570702],"iteration":651,"passed_time":0.6230157625,"remaining_time":0.3325298855},
{"learn":[3.606292637],"iteration":652,"passed_time":0.6236022231,"remaining_time":0.3313782104},
{"learn":[3.602753838],"iteration":653,"passed_time":0.6242227671,"remaining_time":0.3302462957},
{"learn":[3.599755869],"iteration":654,"passed_time":0.6248325986,"remaining_time":0.3291103},
{"learn":[3.599509575],"iteration":655,"passed_time":0.6254265519,"remaining_time":0.3279675821},
{"learn":[3.595337722],"iteration":656,"passed_time":0.6260573772,"remaining_time":0.3268457844},
{"learn":[3.595168561],"iteration":657,"passed_time":0.626638873,"remaining_time":0.3256998397},
{"learn":[3.59290559],"iteration":658,"passed_time":0.6274817019,"remaining_time":0.3246908351},
{"learn":[3.592015928],"iteration":659,"passed_time":0.628186612,"remaining_time":0.323611285},
{"learn":[3.590680403],"iteration":660,"passed_time":0.6288286112,"remaining_time":0.3225006039},
{"learn":[3.590361532],"iteration":661,"passed_time":0.6294262557,"remaining_time":0.3213686925},
{"learn":[3.589069739],"iteration":662,"passed_time":0.6299810702,"remaining_time":0.3202166224},
{"learn":[3.585010186],"iteration":663,"passed_time":0.6305760165,"remaining_time":0.319086659},
{"learn":[3.582997552],"iteration":664,"passed_time":0.6312200117,"remaining_time":0.3179830134},
{"learn":[3.582119256],"iteration":665,"passed_time":0.6318156502,"remaining_time":0.3168564972},
{"learn":[3.579019356],"iteration":666,"passed_time":0.63240516,"remaining_time":0.3157285132},
{"learn":[3.57719559],"iteration":667,"passed_time":0.6330694603,"remaining_time":0.3146393126},
{"learn":[3.574050046],"iteration":668,"passed_time":0.6338072356,"remaining_time":0.3135877354},
{"learn":[3.572204518],"iteration":669,"passed_time":0.6344547114,"remaining_time":0.312492619},
{"learn":[3.569508025],"iteration":670,"passed_time":0.6351745769,"remaining_time":0.3114343306},
{"learn":[3.566268704],"iteration":671,"passed_time":0.6359676858,"remaining_time":0.310412799},
{"learn":[3.562564052],"iteration":672,"passed_time":0.6367459387,"remaining_time":0.309384728},
{"learn":[3.561173586],"iteration":673,"passed_time":0.637340233,"remaining_time":0.3082684213},
{"learn":[3.559551904],"iteration":674,"passed_time":0.6380451322,"remaining_time":0.3072069155},
{"learn":[3.558593054],"iteration":675,"passed_time":0.6387150361,"remaining_time":0.3061296919},
{"learn":[3.555647008],"iteration":676,"passed_time":0.6395548105,"remaining_time":0.3051347175},
{"learn":[3.553100059],"iteration":677,"passed_time":0.6403931705,"remaining_time":0.3041395293},
{"learn":[3.55085578],"iteration":678,"passed_time":0.6411829223,"remaining_time":0.3031218234},
{"learn":[3.550737965],"iteration":679,"passed_time":0.6419309246,"remaining_time":0.302085141},
{"learn":[3.549408772],"iteration":680,"passed_time":0.6425894539,"remaining_time":0.3010073947},
{"learn":[3.547390589],"iteration":681,"passed_time":0.6432043809,"remaining_time":0.2999105471},
{"learn":[3.54723575],"iteration":682,"passed_time":0.643775866,"remaining_time":0.2987949481},
{"learn":[3.543988891],"iteration":683,"passed_time":0.6443677831,"remaining_time":0.2976903793},
{"learn":[3.543868508],"iteration":684,"passed_time":0.6449424178,"remaining_time":0.29657936},
{"learn":[3.542752124],"iteration":685,"passed_time":0.6457184326,"remaining_time":0.2955620814},
{"learn":[3.541334315],"iteration":686,"passed_time":0.6464542065,"remaining_time":0.2945271712},
{"learn":[3.540208266],"iteration":687,"passed_time":0.6471291858,"remaining_time":0.293465561},
{"learn":[3.537730983],"iteration":688,"passed_time":0.6478145967,"remaining_time":0.2924097817},
{"learn":[3.53419867],"iteration":689,"passed_time":0.6485106099,"remaining_time":0.2913598392},
{"learn":[3.532628335],"iteration":690,"passed_time":0.649053779,"remaining_time":0.2902425727},
{"learn":[3.532204987],"iteration":691,"passed_time":0.6497202826,"remaining_time":0.2891818599},
{"learn":[3.530618147],"iteration":692,"passed_time":0.6506480209,"remaining_time":0.2882380121},
{"learn":[3.528909306],"iteration":693,"passed_time":0.6515330125,"remaining_time":0.2872753628},
{"learn":[3.526700678],"iteration":694,"passed_time":0.6526873312,"remaining_time":0.2864311309},
{"learn":[3.526439574],"iteration":695,"passed_time":0.6534704388,"remaining_time":0.2854238698},
{"learn":[3.525784216],"iteration":696,"passed_time":0.6541738444,"remaining_time":0.2843826038},
{"learn":[3.524112693],"iteration":697,"passed_time":0.654863739,"remaining_time":0.2833364601},
{"learn":[3.522813541],"iteration":698,"passed_time":0.6554077406,"remaining_time":0.282228512},
{"learn":[3.519148203],"iteration":699,"passed_time":0.6559735083,"remaining_time":0.2811315036},
{"learn":[3.517236747],"iteration":700,"passed_time":0.6566563716,"remaining_time":0.2800859559},
{"learn":[3.515603888],"iteration":701,"passed_time":0.6572957327,"remaining_time":0.2790229749},
{"learn":[3.51263524],"iteration":702,"passed_time":0.65827945,"remaining_time":0.2781066809},
{"learn":[3.51123442],"iteration":703,"passed_time":0.6590618056,"remaining_time":0.2771055319},
{"learn":[3.50828027],"iteration":704,"passed_time":0.659748671,"remaining_time":0.2760650467},
{"learn":[3.508265537],"iteration":705,"passed_time":0.6602086877,"remaining_time":0.2749310966},
{"learn":[3.506774876],"iteration":706,"passed_time":0.6608407768,"remaining_time":0.2738703643},
{"learn":[3.50552068],"iteration":707,"passed_time":0.6614544499,"remaining_time":0.2728032477},
{"learn":[3.501973993],"iteration":708,"passed_time":0.6620636796,"remaining_time":0.2717355864},
{"learn":[3.498880354],"iteration":709,"passed_time":0.6627912784,"remaining_time":0.2707175644},
{"learn":[3.497370959],"iteration":710,"passed_time":0.6635923505,"remaining_time":0.269730224},
{"learn":[3.496050455],"iteration":711,"passed_time":0.6644546178,"remaining_time":0.26876816},
{"learn":[3.495630067],"iteration":712,"passed_time":0.6653587723,"remaining_time":0.2678232365},
{"learn":[3.49550669],"iteration":713,"passed_time":0.6660937136,"remaining_time":0.2668106472},
{"learn":[3.493652375],"iteration":714,"passed_time":0.6668635315,"remaining_time":0.2658127363},
{"learn":[3.491915684],"iteration":715,"passed_time":0.6675177979,"remaining_time":0.2647696293},
{"learn":[3.490303956],"iteration":716,"passed_time":0.6681493755,"remaining_time":0.2637186517},
{"learn":[3.488363853],"iteration":717,"passed_time":0.6688286879,"remaining_time":0.2626875905},
{"learn":[3.485483936],"iteration":718,"passed_time":0.6693464198,"remaining_time":0.2615943588},
{"learn":[3.483763466],"iteration":719,"passed_time":0.6701884573,"remaining_time":0.2606288445},
{"learn":[3.481642352],"iteration":720,"passed_time":0.6710751089,"remaining_time":0.2596809367},
{"learn":[3.479826119],"iteration":721,"passed_time":0.671768785,"remaining_time":0.258658895},
{"learn":[3.478588728],"iteration":722,"passed_time":0.6724487698,"remaining_time":0.2576325162},
{"learn":[3.475390887],"iteration":723,"passed_time":0.6731063964,"remaining_time":0.256598571},
{"learn":[3.472636852],"iteration":724,"passed_time":0.6736331457,"remaining_time":0.2555160208},
{"learn":[3.47061883],"iteration":725,"passed_time":0.6742520848,"remaining_time":0.2544697951},
{"learn":[3.46953149],"iteration":726,"passed_time":0.6748959497,"remaining_time":0.2534341049},
{"learn":[3.467217162],"iteration":727,"passed_time":0.6755244679,"remaining_time":0.2523937572},
{"learn":[3.465686216],"iteration":728,"passed_time":0.676157871,"remaining_time":0.2513563553},
{"learn":[3.462631216],"iteration":729,"passed_time":0.6769588115,"remaining_time":0.2503820262},
{"learn":[3.461451053],"iteration":730,"passed_time":0.6776408723,"remaining_time":0.249364425},
{"learn":[3.458950469],"iteration":731,"passed_time":0.6788300844,"remaining_time":0.2485334189},
{"learn":[3.458072145],"iteration":732,"passed_time":0.6795083537,"remaining_time":0.2475153212},
{"learn":[3.454364268],"iteration":733,"passed_time":0.6801568326,"remaining_time":0.2464873535},
{"learn":[3.453243406],"iteration":734,"passed_time":0.6808006472,"remaining_time":0.2454587368},
{"learn":[3.453017963],"iteration":735,"passed_time":0.6813775287,"remaining_time":0.244407157},
{"learn":[3.45201581],"iteration":736,"passed_time":0.6819842107,"remaining_time":0.2433674999},
{"learn":[3.449510107],"iteration":737,"passed_time":0.6827296135,"remaining_time":0.2423782639},
{"learn":[3.447189189],"iteration":738,"passed_time":0.6835683001,"remaining_time":0.2414226337},
{"learn":[3.446423605],"iteration":739,"passed_time":0.6843057889,"remaining_time":0.2404317637},
{"learn":[3.445531987],"iteration":740,"passed_time":0.6849420005,"remaining_time":0.2394061783},
{"learn":[3.445328199],"iteration":741,"passed_time":0.6854425301,"remaining_time":0.2383344647},
{"learn":[3.443327544],"iteration":742,"passed_time":0.6860472549,"remaining_time":0.2373003291},
{"learn":[3.441475798],"iteration":743,"passed_time":0.686761826,"remaining_time":0.2363051444},
{"learn":[3.439046501],"iteration":744,"passed_time":0.6875135367,"remaining_time":0.2353234253},
{"learn":[3.435899469],"iteration":745,"passed_time":0.6882889158,"remaining_time":0.2343503815},
{"learn":[3.433988352],"iteration":746,"passed_time":0.6889991732,"remaining_time":0.233355811},
{"learn":[3.433413263],"iteration":747,"passed_time":0.6899378722,"remaining_time":0.2324389623},
{"learn":[3.429944699],"iteration":748,"passed_time":0.6907147408,"remaining_time":0.2314678237},
{"learn":[3.429291634],"iteration":749,"passed_time":0.6915975411,"remaining_time":0.2305325137},
{"learn":[3.429175603],"iteration":750,"passed_time":0.6925186076,"remaining_time":0.229610031},
{"learn":[3.428780323],"iteration":751,"passed_time":0.6934257718,"remaining_time":0.2286829673},
{"learn":[3.423893341],"iteration":752,"passed_time":0.6943133955,"remaining_time":0.2277495467},
{"learn":[3.421024316],"iteration":753,"passed_time":0.6952001543,"remaining_time":0.2268159655},
{"learn":[3.420969872],"iteration":754,"passed_time":0.6961333075,"remaining_time":0.2258975634},
{"learn":[3.419544785],"iteration":755,"passed_time":0.6970085849,"remaining_time":0.2249604427},
{"learn":[3.417057977],"iteration":756,"passed_time":0.6978277118,"remaining_time":0.224005461},
{"learn":[3.415160245],"iteration":757,"passed_time":0.698811558,"remaining_time":0.2231034262},
{"learn":[3.412854597],"iteration":758,"passed_time":0.6997540492,"remaining_time":0.2221880446},
{"learn":[3.410926347],"iteration":759,"passed_time":0.7004797926,"remaining_time":0.221204145},
{"learn":[3.408963843],"iteration":760,"passed_time":0.7014314823,"remaining_time":0.2202918847},
{"learn":[3.407629634],"iteration":761,"passed_time":0.702354594,"remaining_time":0.219370595},
{"learn":[3.404384724],"iteration":762,"passed_time":0.7031008096,"remaining_time":0.2183943537},
{"learn":[3.403041656],"iteration":763,"passed_time":0.7037793607,"remaining_time":0.217397813},
{"learn":[3.401101731],"iteration":764,"passed_time":0.7046245656,"remaining_time":0.2164532979},
{"learn":[3.400890668],"iteration":765,"passed_time":0.7054643515,"remaining_time":0.2155073868},
{"learn":[3.399289941],"iteration":766,"passed_time":0.7064170894,"remaining_time":0.214596065},
{"learn":[3.399202366],"iteration":767,"passed_time":0.7072035804,"remaining_time":0.2136344149},
{"learn":[3.397447845],"iteration":768,"passed_time":0.7081786972,"remaining_time":0.2127298817},
{"learn":[3.394655341],"iteration":769,"passed_time":0.7090652881,"remaining_time":0.2117987224},
{"learn":[3.393228229],"iteration":770,"passed_time":0.7099250393,"remaining_time":0.2108597069},
{"learn":[3.389691197],"iteration":771,"passed_time":0.7107418382,"remaining_time":0.2099082113},
{"learn":[3.389626772],"iteration":772,"passed_time":0.7114112707,"remaining_time":0.2089137884},
{"learn":[3.388480222],"iteration":773,"passed_time":0.712187141,"remaining_time":0.2079512841},
{"learn":[3.388215066],"iteration":774,"passed_time":0.7131543742,"remaining_time":0.2070448183},
{"learn":[3.386324358],"iteration":775,"passed_time":0.7141221722,"remaining_time":0.206138359},
{"learn":[3.383913061],"iteration":776,"passed_time":0.7151247715,"remaining_time":0.2052417298},
{"learn":[3.382839768],"iteration":777,"passed_time":0.7159041315,"remaining_time":0.2042811275},
{"learn":[3.381961844],"iteration":778,"passed_time":0.7165731329,"remaining_time":0.2032896821},
{"learn":[3.381521703],"iteration":779,"passed_time":0.7173098657,"remaining_time":0.2023181672},
{"learn":[3.380918963],"iteration":780,"passed_time":0.7180498276,"remaining_time":0.2013481591},
{"learn":[3.377139006],"iteration":781,"passed_time":0.7188858057,"remaining_time":0.2004055059},
{"learn":[3.376004372],"iteration":782,"passed_time":0.7199764363,"remaining_time":0.1995336995},
{"learn":[3.373826468],"iteration":783,"passed_time":0.7209888802,"remaining_time":0.1986397935},
{"learn":[3.373546786],"iteration":784,"passed_time":0.7219043898,"remaining_time":0.1977190367},
{"learn":[3.372109181],"iteration":785,"passed_time":0.7226927433,"remaining_time":0.1967636731},
{"learn":[3.370764924],"iteration":786,"passed_time":0.7234583478,"remaining_time":0.195802577},
{"learn":[3.367833107],"iteration":787,"passed_time":0.7241278805,"remaining_time":0.1948161303},
{"learn":[3.36450404],"iteration":788,"passed_time":0.7248245256,"remaining_time":0.1938377375},
{"learn":[3.361794558],"iteration":789,"passed_time":0.7255165266,"remaining_time":0.1928588235},
{"learn":[3.356880529],"iteration":790,"passed_time":0.7263384524,"remaining_time":0.191914964},
{"learn":[3.353843509],"iteration":791,"passed_time":0.7274675551,"remaining_time":0.1910520852},
{"learn":[3.353640253],"iteration":792,"passed_time":0.7283249323,"remaining_time":0.1901176053},
{"learn":[3.353055088],"iteration":793,"passed_time":0.7291089222,"remaining_time":0.1891642796},
{"learn":[3.351415617],"iteration":794,"passed_time":0.7298913778,"remaining_time":0.1882109842},
{"learn":[3.349169061],"iteration":795,"passed_time":0.7306306335,"remaining_time":0.1872470468},
{"learn":[3.346211014],"iteration":796,"passed_time":0.7314317994,"remaining_time":0.186299442},
{"learn":[3.344560452],"iteration":797,"passed_time":0.7322773864,"remaining_time":0.1853634487},
{"learn":[3.344445461],"iteration":798,"passed_time":0.7331955352,"remaining_time":0.1844459356},
{"learn":[3.342608898],"iteration":799,"passed_time":0.734261311,"remaining_time":0.1835653278},
{"learn":[3.339572899],"iteration":800,"passed_time":0.7351486334,"remaining_time":0.1826399227},
{"learn":[3.339309302],"iteration":801,"passed_time":0.7357619355,"remaining_time":0.1816469616},
{"learn":[3.33698088],"iteration":802,"passed_time":0.736475333,"remaining_time":0.1806795026},
{"learn":[3.334746342],"iteration":803,"passed_time":0.7372047676,"remaining_time":0.1797165851},
{"learn":[3.332048511],"iteration":804,"passed_time":0.7377844877,"remaining_time":0.1787179815},
{"learn":[3.331932544],"iteration":805,"passed_time":0.7387744421,"remaining_time":0.1778191585},
{"learn":[3.330541133],"iteration":806,"passed_time":0.7397080626,"remaining_time":0.176906637},
{"learn":[3.329124989],"iteration":807,"passed_time":0.7404975796,"remaining_time":0.1759598209},
{"learn":[3.32583918],"iteration":808,"passed_time":0.7412359053,"remaining_time":0.1750013077},
{"learn":[3.325287299],"iteration":809,"passed_time":0.7420290647,"remaining_time":0.1740562004},
{"learn":[3.322745162],"iteration":810,"passed_time":0.7428128531,"remaining_time":0.1731092839},
{"learn":[3.319733662],"iteration":811,"passed_time":0.7435773442,"remaining_time":0.1721583014},
{"learn":[3.318080007],"iteration":812,"passed_time":0.7444113005,"remaining_time":0.1712237555},
{"learn":[3.317179538],"iteration":813,"passed_time":0.7455422106,"remaining_time":0.170357311},
{"learn":[3.315685949],"iteration":814,"passed_time":0.7464232258,"remaining_time":0.169433493},
{"learn":[3.314944576],"iteration":815,"passed_time":0.7471624301,"remaining_time":0.1684778029},
{"learn":[3.312369052],"iteration":816,"passed_time":0.7481619695,"remaining_time":0.1675809552},
{"learn":[3.312321621],"iteration":817,"passed_time":0.7490946449,"remaining_time":0.1666689797},
{"learn":[3.309465776],"iteration":818,"passed_time":0.7499429116,"remaining_time":0.1657382991},
{"learn":[3.308307377],"iteration":819,"passed_time":0.7507997013,"remaining_time":0.1648096905},
{"learn":[3.308076804],"iteration":820,"passed_time":0.7519001765,"remaining_time":0.1639343868},
{"learn":[3.305643326],"iteration":821,"passed_time":0.752794814,"remaining_time":0.1630139622},
{"learn":[3.304154814],"iteration":822,"passed_time":0.7535874653,"remaining_time":0.1620716663},
{"learn":[3.303076321],"iteration":823,"passed_time":0.7543419312,"remaining_time":0.1611215775},
{"learn":[3.301746372],"iteration":824,"passed_time":0.7551127904,"remaining_time":0.1601754404},
{"learn":[3.301345455],"iteration":825,"passed_time":0.7559869456,"remaining_time":0.1592514873},
{"learn":[3.299181039],"iteration":826,"passed_time":0.7569821058,"remaining_time":0.1583529677},
{"learn":[3.297989357],"iteration":827,"passed_time":0.7580863289,"remaining_time":0.1574768703},
{"learn":[3.294775182],"iteration":828,"passed_time":0.7589660903,"remaining_time":0.1565539221},
{"learn":[3.293840636],"iteration":829,"passed_time":0.7598435747,"remaining_time":0.1556306117},
{"learn":[3.289279397],"iteration":830,"passed_time":0.7605685358,"remaining_time":0.154676393},
{"learn":[3.286204979],"iteration":831,"passed_time":0.7613720839,"remaining_time":0.1537385939},
{"learn":[3.284833593],"iteration":832,"passed_time":0.7621497264,"remaining_time":0.1527959235},
{"learn":[3.283519914],"iteration":833,"passed_time":0.763277761,"remaining_time":0.1519233913},
{"learn":[3.282853026],"iteration":834,"passed_time":0.76431197,"remaining_time":0.1510317066},
{"learn":[3.281944673],"iteration":835,"passed_time":0.7651403864,"remaining_time":0.1500993102},
{"learn":[3.279764865],"iteration":836,"passed_time":0.7659266232,"remaining_time":0.1491589481},
{"learn":[3.277468839],"iteration":837,"passed_time":0.7666812543,"remaining_time":0.1482128439},
{"learn":[3.277124974],"iteration":838,"passed_time":0.7674100069,"remaining_time":0.1472622302},
{"learn":[3.275636037],"iteration":839,"passed_time":0.7681532534,"remaining_time":0.1463149054},
{"learn":[3.274413635],"iteration":840,"passed_time":0.7688369392,"remaining_time":0.1453568054},
{"learn":[3.272636087],"iteration":841,"passed_time":0.7698180376,"remaining_time":0.1444551662},
{"learn":[3.269644466],"iteration":842,"passed_time":0.7707746908,"remaining_time":0.1435487858},
{"learn":[3.26852083],"iteration":843,"passed_time":0.7715672283,"remaining_time":0.1426119521},
{"learn":[3.267820927],"iteration":844,"passed_time":0.772264074,"remaining_time":0.1416579071},
{"learn":[3.267331099],"iteration":845,"passed_time":0.7729029035,"remaining_time":0.1406939092},
{"learn":[3.267231014],"iteration":846,"passed_time":0.7735260755,"remaining_time":0.1397278507},
{"learn":[3.267158695],"iteration":847,"passed_time":0.7741309119,"remaining_time":0.1387593144},
{"learn":[3.264718705],"iteration":848,"passed_time":0.7747801129,"remaining_time":0.1377995254},
{"learn":[3.261678512],"iteration":849,"passed_time":0.7755877149,"remaining_time":0.1368684203},
{"learn":[3.261368381],"iteration":850,"passed_time":0.7764949293,"remaining_time":0.1359550464},
{"learn":[3.260128799],"iteration":851,"passed_time":0.7774432889,"remaining_time":0.1350488342},
{"learn":[3.258972952],"iteration":852,"passed_time":0.7782647329,"remaining_time":0.1341206515},
{"learn":[3.258724846],"iteration":853,"passed_time":0.7789489502,"remaining_time":0.1331692585},
{"learn":[3.25686724],"iteration":854,"passed_time":0.7796809627,"remaining_time":0.132226596},
{"learn":[3.255750259],"iteration":855,"passed_time":0.7803930939,"remaining_time":0.1312810812},
{"learn":[3.254915866],"iteration":856,"passed_time":0.7811887596,"remaining_time":0.1303500497},
{"learn":[3.254348625],"iteration":857,"passed_time":0.7822721047,"remaining_time":0.1294669451},
{"learn":[3.253408514],"iteration":858,"passed_time":0.7831946415,"remaining_time":0.1285569784},
{"learn":[3.253291714],"iteration":859,"passed_time":0.7841402371,"remaining_time":0.1276507363},
{"learn":[3.250186342],"iteration":860,"passed_time":0.7850462679,"remaining_time":0.1267380154},
{"learn":[3.249141318],"iteration":861,"passed_time":0.7857714396,"remaining_time":0.1257963558},
{"learn":[3.246300388],"iteration":862,"passed_time":0.7865128998,"remaining_time":0.1248577836},
{"learn":[3.245205135],"iteration":863,"passed_time":0.7873812672,"remaining_time":0.1239396439},
{"learn":[3.244403535],"iteration":864,"passed_time":0.7885477485,"remaining_time":0.1230681457},
{"learn":[3.244211781],"iteration":865,"passed_time":0.7895551207,"remaining_time":0.1221713466},
{"learn":[3.242286347],"iteration":866,"passed_time":0.7904257177,"remaining_time":0.1212533108},
{"learn":[3.239606746],"iteration":867,"passed_time":0.7913318353,"remaining_time":0.120340786},
{"learn":[3.236773361],"iteration":868,"passed_time":0.7921506096,"remaining_time":0.1194151092},
{"learn":[3.234552446],"iteration":869,"passed_time":0.792927851,"remaining_time":0.118483472},
{"learn":[3.233724647],"iteration":870,"passed_time":0.7937753939,"remaining_time":0.1175626014},
{"learn":[3.230851485],"iteration":871,"passed_time":0.7946399503,"remaining_time":0.1166443964},
{"learn":[3.227728941],"iteration":872,"passed_time":0.7956526951,"remaining_time":0.115747872},
{"learn":[3.225787575],"iteration":873,"passed_time":0.7964616308,"remaining_time":0.1148216996},
{"learn":[3.222797487],"iteration":874,"passed_time":0.7972170744,"remaining_time":0.1138881535},
{"learn":[3.22137014],"iteration":875,"passed_time":0.7981238528,"remaining_time":0.1129764358},
{"learn":[3.219701963],"iteration":876,"passed_time":0.798836015,"remaining_time":0.1120374343},
{"learn":[3.21783327],"iteration":877,"passed_time":0.7996400461,"remaining_time":0.1111117148},
{"learn":[3.217713355],"iteration":878,"passed_time":0.8005690855,"remaining_time":0.1102034805},
{"learn":[3.217666091],"iteration":879,"passed_time":0.8014332696,"remaining_time":0.1092863549},
{"learn":[3.214962005],"iteration":880,"passed_time":0.8022161176,"remaining_time":0.1083583632},
{"learn":[3.214081828],"iteration":881,"passed_time":0.8029761198,"remaining_time":0.1074276441},
{"learn":[3.213358337],"iteration":882,"passed_time":0.8039059027,"remaining_time":0.1065198082},
{"learn":[3.210850401],"iteration":883,"passed_time":0.8046791857,"remaining_time":0.1055913864},
{"learn":[3.207810328],"iteration":884,"passed_time":0.8055573557,"remaining_time":0.1046769445},
{"learn":[3.204935073],"iteration":885,"passed_time":0.8065442034,"remaining_time":0.1037765679},
{"learn":[3.20280198],"iteration":886,"passed_time":0.807533487,"remaining_time":0.1028763067},
{"learn":[3.200663495],"iteration":887,"passed_time":0.8083231993,"remaining_time":0.1019506738},
{"learn":[3.197301669],"iteration":888,"passed_time":0.8090496888,"remaining_time":0.1010174527},
{"learn":[3.195666943],"iteration":889,"passed_time":0.8097529703,"remaining_time":0.1000818278},
{"learn":[3.193886506],"iteration":890,"passed_time":0.8104900381,"remaining_time":0.09915085763},
{"learn":[3.190601248],"iteration":891,"passed_time":0.8113047015,"remaining_time":0.09822971722},
{"learn":[3.188983797],"iteration":892,"passed_time":0.8122973101,"remaining_time":0.09733013682},
{"learn":[3.187365749],"iteration":893,"passed_time":0.8132909557,"remaining_time":0.09643047126},
{"learn":[3.186160771],"iteration":894,"passed_time":0.814203437,"remaining_time":0.09552107361},
{"learn":[3.185358981],"iteration":895,"passed_time":0.8150220863,"remaining_time":0.09460077787},
{"learn":[3.183832164],"iteration":896,"passed_time":0.8158104451,"remaining_time":0.0936772306},
{"learn":[3.183106966],"iteration":897,"passed_time":0.8165569124,"remaining_time":0.09274922613},
{"learn":[3.182838152],"iteration":898,"passed_time":0.8172321262,"remaining_time":0.0918136204},
{"learn":[3.180835453],"iteration":899,"passed_time":0.8180174069,"remaining_time":0.09089082299},
{"learn":[3.179957348],"iteration":900,"passed_time":0.8189075692,"remaining_time":0.089979855},
{"learn":[3.179752966],"iteration":901,"passed_time":0.8199858483,"remaining_time":0.08908937154},
{"learn":[3.178851983],"iteration":902,"passed_time":0.820920911,"remaining_time":0.08818308789},
{"learn":[3.176748586],"iteration":903,"passed_time":0.8218023173,"remaining_time":0.08727104255},
{"learn":[3.172960988],"iteration":904,"passed_time":0.8224816699,"remaining_time":0.08633785485},
{"learn":[3.172794225],"iteration":905,"passed_time":0.8231230171,"remaining_time":0.08540128434},
{"learn":[3.169996507],"iteration":906,"passed_time":0.8237801121,"remaining_time":0.08446697952},
{"learn":[3.16813015],"iteration":907,"passed_time":0.8244958251,"remaining_time":0.08353922457},
{"learn":[3.166920871],"iteration":908,"passed_time":0.8254248269,"remaining_time":0.0826332885},
{"learn":[3.16531606],"iteration":909,"passed_time":0.8264369692,"remaining_time":0.08173552443},
{"learn":[3.162035247],"iteration":910,"passed_time":0.8273786081,"remaining_time":0.08083062143},
{"learn":[3.16189467],"iteration":911,"passed_time":0.8281181836,"remaining_time":0.07990614052},
{"learn":[3.161008416],"iteration":912,"passed_time":0.8288813208,"remaining_time":0.07898430987},
{"learn":[3.160560787],"iteration":913,"passed_time":0.8295016238,"remaining_time":0.07804938692},
{"learn":[3.160416261],"iteration":914,"passed_time":0.8302401413,"remaining_time":0.07712613335},
{"learn":[3.15844291],"iteration":915,"passed_time":0.8312602635,"remaining_time":0.07622910714},
{"learn":[3.155040501],"iteration":916,"passed_time":0.8321966151,"remaining_time":0.07532423016},
{"learn":[3.154937548],"iteration":917,"passed_time":0.8331440727,"remaining_time":0.07442027664},
{"learn":[3.153721161],"iteration":918,"passed_time":0.8340803644,"remaining_time":0.0735152443},
{"learn":[3.153170511],"iteration":919,"passed_time":0.8351496418,"remaining_time":0.07262170798},
{"learn":[3.153113601],"iteration":920,"passed_time":0.835996082,"remaining_time":0.07170867587},
{"learn":[3.150607379],"iteration":921,"passed_time":0.8366960471,"remaining_time":0.07078339661},
{"learn":[3.148408359],"iteration":922,"passed_time":0.8377254914,"remaining_time":0.06988609191},
{"learn":[3.147495728],"iteration":923,"passed_time":0.838585042,"remaining_time":0.06897452726},
{"learn":[3.146946235],"iteration":924,"passed_time":0.8393021028,"remaining_time":0.06805152185},
{"learn":[3.14472738],"iteration":925,"passed_time":0.8400630293,"remaining_time":0.0671324667},
{"learn":[3.144469477],"iteration":926,"passed_time":0.8409036816,"remaining_time":0.06622003102},
{"learn":[3.142975516],"iteration":927,"passed_time":0.8417377439,"remaining_time":0.06530723875},
{"learn":[3.14079113],"iteration":928,"passed_time":0.8424947761,"remaining_time":0.06438872885},
{"learn":[3.138173032],"iteration":929,"passed_time":0.8434707292,"remaining_time":0.06348704413},
{"learn":[3.136352813],"iteration":930,"passed_time":0.8443958746,"remaining_time":0.06258143431},
{"learn":[3.133735004],"iteration":931,"passed_time":0.8452439729,"remaining_time":0.06167016111},
{"learn":[3.1319496],"iteration":932,"passed_time":0.8461220253,"remaining_time":0.06076117438},
{"learn":[3.129865343],"iteration":933,"passed_time":0.8469541715,"remaining_time":0.05984900998},
{"learn":[3.129830206],"iteration":934,"passed_time":0.8477739808,"remaining_time":0.05893615909},
{"learn":[3.126676562],"iteration":935,"passed_time":0.8487258411,"remaining_time":0.05803253614},
{"learn":[3.12645665],"iteration":936,"passed_time":0.8498760416,"remaining_time":0.05714214581},
{"learn":[3.126378007],"iteration":937,"passed_time":0.8507987531,"remaining_time":0.05623616492},
{"learn":[3.124621914],"iteration":938,"passed_time":0.8517169809,"remaining_time":0.05532985712},
{"learn":[3.123379018],"iteration":939,"passed_time":0.8524614816,"remaining_time":0.054412435},
{"learn":[3.123332451],"iteration":940,"passed_time":0.8532082689,"remaining_time":0.05349552377},
{"learn":[3.122432444],"iteration":941,"passed_time":0.8538787847,"remaining_time":0.05257427761},
{"learn":[3.121889006],"iteration":942,"passed_time":0.8545281663,"remaining_time":0.05165228577},
{"learn":[3.121070914],"iteration":943,"passed_time":0.8553380451,"remaining_time":0.05074039251},
{"learn":[3.118444705],"iteration":944,"passed_time":0.8562872517,"remaining_time":0.04983682417},
{"learn":[3.116820458],"iteration":945,"passed_time":0.8572289254,"remaining_time":0.04893272936},
{"learn":[3.114971041],"iteration":946,"passed_time":0.8582974483,"remaining_time":0.04803565445},
{"learn":[3.114685138],"iteration":947,"passed_time":0.859280182,"remaining_time":0.04713351209},
{"learn":[3.113399363],"iteration":948,"passed_time":0.8599205161,"remaining_time":0.04621279907},
{"learn":[3.110575399],"iteration":949,"passed_time":0.8605822652,"remaining_time":0.04529380343},
{"learn":[3.110466553],"iteration":950,"passed_time":0.8616387613,"remaining_time":0.04439568802},
{"learn":[3.108691641],"iteration":951,"passed_time":0.8626654688,"remaining_time":0.04349573792},
{"learn":[3.107898017],"iteration":952,"passed_time":0.8633783632,"remaining_time":0.0425800452},
{"learn":[3.105551729],"iteration":953,"passed_time":0.8640359297,"remaining_time":0.04166210982},
{"learn":[3.104824945],"iteration":954,"passed_time":0.8647328456,"remaining_time":0.04074657387},
{"learn":[3.103186704],"iteration":955,"passed_time":0.8653767204,"remaining_time":0.03982905408},
{"learn":[3.102330655],"iteration":956,"passed_time":0.8660096019,"remaining_time":0.03891161221},
{"learn":[3.102291298],"iteration":957,"passed_time":0.8665997537,"remaining_time":0.03799289108},
{"learn":[3.100363529],"iteration":958,"passed_time":0.8674468151,"remaining_time":0.03708583881},
{"learn":[3.097871596],"iteration":959,"passed_time":0.8683699541,"remaining_time":0.03618208142},
{"learn":[3.097372213],"iteration":960,"passed_time":0.8692572317,"remaining_time":0.03527682834},
{"learn":[3.095981813],"iteration":961,"passed_time":0.870092078,"remaining_time":0.03436954154},
{"learn":[3.095347452],"iteration":962,"passed_time":0.8708383537,"remaining_time":0.03345900217},
{"learn":[3.094728409],"iteration":963,"passed_time":0.8715879182,"remaining_time":0.03254892641},
{"learn":[3.094118537],"iteration":964,"passed_time":0.8722411415,"remaining_time":0.03163568907},
{"learn":[3.093793695],"iteration":965,"passed_time":0.8728279531,"remaining_time":0.03072065259},
{"learn":[3.092581602],"iteration":966,"passed_time":0.8735911415,"remaining_time":0.02981231403},
{"learn":[3.091694202],"iteration":967,"passed_time":0.874553492,"remaining_time":0.02891085924},
{"learn":[3.090298312],"iteration":968,"passed_time":0.8756555022,"remaining_time":0.02801374672},
{"learn":[3.090020107],"iteration":969,"passed_time":0.8766235676,"remaining_time":0.0271120691},
{"learn":[3.088949869],"iteration":970,"passed_time":0.877370395,"remaining_time":0.02620364723},
{"learn":[3.086700204],"iteration":971,"passed_time":0.8780694173,"remaining_time":0.02529418075},
{"learn":[3.086584317],"iteration":972,"passed_time":0.8786874337,"remaining_time":0.02438289898},
{"learn":[3.084850742],"iteration":973,"passed_time":0.8794574114,"remaining_time":0.02347627587},
{"learn":[3.084239948],"iteration":974,"passed_time":0.8802999598,"remaining_time":0.02257179384},
{"learn":[3.082561673],"iteration":975,"passed_time":0.8812258199,"remaining_time":0.02166948737},
{"learn":[3.07991814],"iteration":976,"passed_time":0.8821757038,"remaining_time":0.02076769825},
{"learn":[3.079350277],"iteration":977,"passed_time":0.8832205056,"remaining_time":0.01986794593},
{"learn":[3.077637462],"iteration":978,"passed_time":0.8839766514,"remaining_time":0.01896170549},
{"learn":[3.076733301],"iteration":979,"passed_time":0.8847497294,"remaining_time":0.01805611693},
{"learn":[3.07594065],"iteration":980,"passed_time":0.8854677648,"remaining_time":0.01714973245},
{"learn":[3.072594655],"iteration":981,"passed_time":0.8864674311,"remaining_time":0.01624889385},
{"learn":[3.071977674],"iteration":982,"passed_time":0.8873121304,"remaining_time":0.01534517418},
{"learn":[3.069532634],"iteration":983,"passed_time":0.8881586906,"remaining_time":0.01444160473},
{"learn":[3.068870784],"iteration":984,"passed_time":0.8888589868,"remaining_time":0.01353592366},
{"learn":[3.068801463],"iteration":985,"passed_time":0.8897301358,"remaining_time":0.01263308509},
{"learn":[3.067433249],"iteration":986,"passed_time":0.8905167299,"remaining_time":0.01172919705},
{"learn":[3.065611456],"iteration":987,"passed_time":0.8912025621,"remaining_time":0.01082432262},
{"learn":[3.063039162],"iteration":988,"passed_time":0.8919902577,"remaining_time":0.0099210241},
{"learn":[3.06177873],"iteration":989,"passed_time":0.8928060345,"remaining_time":0.009018242773},
{"learn":[3.061689148],"iteration":990,"passed_time":0.8935742422,"remaining_time":0.008115205025},
{"learn":[3.058984039],"iteration":991,"passed_time":0.8943965836,"remaining_time":0.007212875674},
{"learn":[3.057492984],"iteration":992,"passed_time":0.8951527732,"remaining_time":0.0063102411},
{"learn":[3.057290731],"iteration":993,"passed_time":0.8958444432,"remaining_time":0.005407511729},
{"learn":[3.056068348],"iteration":994,"passed_time":0.8965413506,"remaining_time":0.004505232918},
{"learn":[3.054987307],"iteration":995,"passed_time":0.8973824336,"remaining_time":0.003603945516},
{"learn":[3.054200234],"iteration":996,"passed_time":0.8982188718,"remaining_time":0.00270276491},
{"learn":[3.052732869],"iteration":997,"passed_time":0.8992754403,"remaining_time":0.001802155191},
{"learn":[3.051787862],"iteration":998,"passed_time":0.9002475615,"remaining_time":0.0009011487102},
{"learn":[3.051366222],"iteration":999,"passed_time":0.9011428998,"remaining_time":0}
]}